APB/APB_completer.v



// APB completer module

module APB_completer(

		input reg PCLK, //clock signal

		input reg ENABLE_DMA,	// to initialize state variable and other signals

	// ports to memory manager
		output reg enable,	// enable for mem manager, forwards PENABLE
		input reg ready,	// ready driven by mem manager, forwarded to PREADY
		output reg[7:0] addr,	// address bus for mem manager
		output reg[7:0] data_w,	// data write bus for mem manager
		input reg[7:0] data_r,	// data read bus
		output reg dir,		// r/w signal
		input reg error,	// error signal from mem manager


	// buses and signals to requester, APB
		input reg[7:0] PWDATA,  // data write bus (incoming)
		output reg[7:0] PRDATA, // data read bus(outgoing)
		input reg[7:0] PADDR, 	// address bus
		input reg PSEL, 	// select line for this peripheral
		input reg PWRITE, 	// r/w control line, write=1, read=0
		input reg PENABLE, 	// enable signal for APB r/w
		output reg PREADY,	// ready signal		
		output reg PSLVERR	// signals error when invalid addr or restricted r/w


);


reg[1:0] state; // state variable for FSM


// initializing state variable and other buses and signals.
always @(posedge ENABLE_DMA)
begin
	
	state <= 2'b00;

	enable <= 0;
	addr <= 8'bz;
	data_w <= 8'bz;
	dir <= 1'bz;
	PRDATA <= 8'bz;
	//PREADY <= 0;
	PSLVERR <= 0;

end


// enable ready logic
always @(posedge ready)
begin
	enable <= 0;
end




// APB completer FSM
always @(posedge PCLK)
begin
	
	case(state)
		
		2'b00 : begin
			//PREADY <= 0;
			PRDATA <= 8'bz;
			PSLVERR <= 0;
			if(PSEL==1)
				begin
				state <= 2'b01;
				end
			if(PWRITE==1)
				begin
				data_w <= PWDATA;
				end
			end
		
		2'b01 : begin

				addr <= PADDR;
				dir <= PWRITE;

				state <= 2'b10;

			end

		2'b10 : begin
			if(ready==1 || error==1)
				begin
				case(PWRITE)
	
					0 : begin
						PRDATA <= data_r;
					    end

				endcase
	
				PREADY <= 1;
				enable <= 0;
				state <= 2'b00;
				PSLVERR <= error;
				end
			end


	endcase

end


always @(posedge PENABLE)
begin
	enable <= 1;
end

always @(ready)
begin
	PREADY <= ready;
end



endmodule

APB/APB_requester.v



// APB interface module
module APB_requester(

	input reg PCLK,	// clock signal

	input reg ENABLE_DMA,	// to initialize state variable, buses and signals

// ports for master peripheral (here master is DMA)
	input reg[7:0] data_w, 	// data to write to the peripheral
	output reg[7:0] data_r, // data read from the peripheral
	input reg[7:0] addr, 	// address of memory or register to r/w data
	input reg dir,		// direction of data transfer write=1, read=0
	output reg error,	// error signal for invalid address or direction
	input reg enable,	// enable signal to begin transfer, initialize state variable, masterclock gating
	output reg ready, 	// signals the completion of transfer

// APB buses and control signals
	output reg[7:0] PWDATA, // data write bus
	input reg[7:0] PRDATA,  // data read bus
	output reg[7:0] PADDR,	 // address bus
	output reg[1:0] PSEL,	 // select lines, 1 for each peripheral. here, PSEL[1] for UART and PSEL[0] for memory
	output reg PWRITE,	 // read/write control line, write=1, read=0
	output reg PENABLE, 	 // enable signal for APB
	input reg[1:0] PREADY,	 // ready signals, PREADY[1] for UART and PREADY[0] for memory
	input reg[1:0] PSLVERR		// error response, used to indicate invalid address or direction.
);



// MEMORY_X_ADDR => memory address range
// UART_X_ADDR => UART TX and RX reg addresses
parameter MEMORY_STRT_ADDR = 8'h00, MEMORY_END_ADDR = 8'h7f, UART_TX_ADDR = 8'h80, UART_RX_ADDR = 8'h81, WIDTH = 7;



reg[1:0] state; //state variable
reg PERIPHERAL_INDEX; // used as index for PREADY and PSLVERR


// initializing state variable on ENABLE_DMA, DMA is enabled once and not disabled even if TXI or RXI is raised
always @(posedge ENABLE_DMA)
begin
	state <= 2'b00;
	PSEL <= 2'b00;
	PWRITE <= 1'bz;
	PWDATA <= 8'bz;
	PADDR <= 8'bz;
	error <= 0;
	data_r <= 8'bz;
end


// On positive edge of enable, ready pulled LOW, PWRITE initialized, data_x written to the PXDATA, addr written to PADDR
always @(posedge enable)
begin
	error <= 0;
	ready <= 0;
	PWRITE <= dir; 	// setting PWRITE
	
	// setting data bus according to dir input by master peripheral.
	case(dir)
		1 : PWDATA <= data_w;
	endcase
	PADDR <= addr;
	PENABLE <= 0;

end


// On posedge of enable, drive PSELx to HIGH based on the addr, ie. address to PSEL mapping and initializing PERIPHERAL_INDEX to be used as index in the FSM.
always @(posedge enable)
begin
	if(addr[WIDTH:0] >= MEMORY_STRT_ADDR && addr[WIDTH:0] <= MEMORY_END_ADDR)
	begin
		PSEL[0] = 1;
		PERIPHERAL_INDEX = 1'b0;
	end

	else if(addr == UART_RX_ADDR || addr == UART_TX_ADDR)
	begin
		PSEL[1] = 1;
		PERIPHERAL_INDEX = 1'b1;
	end
end



// FSM
always @(posedge PCLK)
begin
	
	case(state)
		2'b00 : begin
			
			if(PSEL[1:0] != 2'b00)
				begin
				state <= 2'b01;
				PENABLE <= 1;
				end
			end

		// SETUP
		2'b01 : begin
			//PENABLE <= 1;
			state <= 2'b10;
			end

		// ACCESS
		2'b10 : begin

			// for optional wait state
			if(PREADY[PERIPHERAL_INDEX]==1)
				begin
				// checks only the specific line to the selected peripheral
				case({PREADY[PERIPHERAL_INDEX], PSLVERR[PERIPHERAL_INDEX]})
				2'b10 : begin
				
					case(PWRITE)
						1 : begin
							// keeping data bus in high impedance after transfer
							PWDATA <= 8'bz;
						end

						0 : begin
							// reading data to data_r (giving to master peripheral)
							data_r <= PRDATA;
						end
					endcase
					// pulling addr bus and pwrite to high impedance after transfer is complete, also signalling 
					// transfer complete to master peripheral by pulling ready HIGH
					PADDR <= 8'bz;
					PWRITE <= 1'bz;
					ready <= 1;
					state <= 2'b00;
					PSEL <= 2'b00;
					PENABLE <= 0;
					PADDR <= 8'bz;
					PWDATA <= 8'bz;
					end

				// error HIGH, forwards to master and goes to state 00
				2'b11 : begin 
						state <= 2'b00;
						PSEL <= 2'b00;
						PENABLE <= 0;
						ready <= 1;
						error <= 1; // propogated to the CPU
						PADDR <= 8'bz;
						PWDATA <= 8'bz;
						PWRITE <= 1'bz;
					end

				// remains in ACCESS state
				2'b0x : begin
					state <= 2'b10;
					end
				endcase
				end
				
			end

	endcase

end




endmodule

APB/APB_req_comp_tb.v



module APB_req_comp_tb;


reg ENABLE_DMA;
reg master_clk;	// PCLK


// APB BUS
wire[7:0] PWDATA;
wire [7:0] PADDR;
wire [1:0] PSEL;
wire PWRITE;
wire PENABLE;
wire[7:0] PRDATA;
wire[1:0] PREADY;
wire[1:0] PSLVERR;





// inputs to dut1 requester
reg[7:0] data_w_req;
reg[7:0] addr_req;
reg dir_req;
reg enable_req;


// outputs from dut1 requester
wire[7:0] data_r_req;
wire error_req;
wire ready_req;



// inputs to dut2 completer
reg[7:0] data_r_comp;
reg ready_comp;
reg error_comp;


//outputs from dut2 completer
wire[7:0] addr_comp;
wire dir_comp;
wire enable_comp;
wire[7:0] data_w_comp;



integer test_with_wait_state;



reg[7:0] data_to_write; // from requester
reg[7:0] data_written; // to completer

reg[7:0] data_to_read;  // from completer
reg[7:0] data_read; 	// to requester



APB_requester dut1(.PCLK(master_clk), .ENABLE_DMA(ENABLE_DMA), .data_w(data_w_req), .data_r(data_r_req), .addr(addr_req), .dir(dir_req), .error(error_req), .enable(enable_req), .ready(ready_req), .PWDATA(PWDATA), .PRDATA(PRDATA), .PADDR(PADDR), .PSEL(PSEL), .PWRITE(PWRITE), .PENABLE(PENABLE), .PREADY(PREADY), .PSLVERR(PSLVERR));



APB_completer dut2(.PCLK(master_clk), .ENABLE_DMA(ENABLE_DMA), .data_w(data_w_comp), .data_r(data_r_comp), .addr(addr_comp), .dir(dir_comp), .error(error_comp), .enable(enable_comp), .ready(ready_comp), .PWDATA(PWDATA), .PRDATA(PRDATA), .PADDR(PADDR), .PSEL(PSEL[0]), .PWRITE(PWRITE), .PENABLE(PENABLE), .PREADY(PREADY[0]), .PSLVERR(PSLVERR[0]));



//ready for requester side
always @(posedge ready_req)
begin
	enable_req <= 0;
	dir_req <= 1'bz;
	addr_req <= 8'bz;

	if(dir_req==0)
	data_read <= data_r_req;

end

always @(posedge enable_comp)
begin
	if(test_with_wait_state==0)
		begin
		if(dir_comp==0)
			data_r_comp = data_to_read;
		else
			data_written = data_w_comp;
		end
	else
		begin
		ready_comp = 0;
		#5;
		ready_comp = 1;
		if(dir_comp==0)
			data_r_comp = data_to_read;
		else
			data_written = data_w_comp;

		end
	
end



always #1 master_clk = ~master_clk;

initial begin
$dumpfile("APB.vcd");
$dumpvars();



ready_comp = 1;
error_comp = 0;


data_to_read = 8'h67;

data_w_req = 8'bz;

data_r_comp = 8'bz;



master_clk = 0;

enable_req = 0;

ENABLE_DMA = 0;
#5;
ENABLE_DMA = 1;
#1;


data_to_write = 8'h67;
// testing write operation with wait state.
test_with_wait_state = 1;
data_w_req = data_to_write;
addr_req = 8'h67;
dir_req = 1;
enable_req = 1;
#16;


data_to_write = 8'd67;
// testing write operation without wait state
test_with_wait_state = 0;
data_w_req = data_to_write;
addr_req = 8'h67;
dir_req = 1;
enable_req = 1;
#20;


data_to_read = 8'h67;
// testing read operation with wait state
test_with_wait_state = 1;
//data_w_req = data_to_write;
addr_req = 8'h67;
dir_req = 0;
enable_req = 1;
#16;

data_to_read = 8'd67;
// testing write operation without wait state
test_with_wait_state = 0;
//data_w_req = data_to_write;
addr_req = 8'h67;
dir_req = 0;
enable_req = 1;
#16;



$finish;
end


endmodule

APB/APB.vcd
$date
	Tue Jun  9 10:54:00 2026
$end
$version
	Icarus Verilog
$end
$timescale
	1s
$end
$scope module APB_req_comp_tb $end
$var wire 1 ! ready_req $end
$var wire 1 " error_req $end
$var wire 1 # enable_comp $end
$var wire 1 $ dir_comp $end
$var wire 8 % data_w_comp [7:0] $end
$var wire 8 & data_r_req [7:0] $end
$var wire 8 ' addr_comp [7:0] $end
$var wire 1 ( PWRITE $end
$var wire 8 ) PWDATA [7:0] $end
$var wire 2 * PSLVERR [1:0] $end
$var wire 2 + PSEL [1:0] $end
$var wire 2 , PREADY [1:0] $end
$var wire 8 - PRDATA [7:0] $end
$var wire 1 . PENABLE $end
$var wire 8 / PADDR [7:0] $end
$var reg 1 0 ENABLE_DMA $end
$var reg 8 1 addr_req [7:0] $end
$var reg 8 2 data_r_comp [7:0] $end
$var reg 8 3 data_read [7:0] $end
$var reg 8 4 data_to_read [7:0] $end
$var reg 8 5 data_to_write [7:0] $end
$var reg 8 6 data_w_req [7:0] $end
$var reg 8 7 data_written [7:0] $end
$var reg 1 8 dir_req $end
$var reg 1 9 enable_req $end
$var reg 1 : error_comp $end
$var reg 1 ; master_clk $end
$var reg 1 < ready_comp $end
$var integer 32 = test_with_wait_state [31:0] $end
$scope module dut1 $end
$var wire 1 0 ENABLE_DMA $end
$var wire 1 ; PCLK $end
$var wire 2 > PREADY [1:0] $end
$var wire 2 ? PSLVERR [1:0] $end
$var wire 8 @ addr [7:0] $end
$var wire 8 A data_w [7:0] $end
$var wire 1 8 dir $end
$var wire 1 9 enable $end
$var wire 8 B PRDATA [7:0] $end
$var parameter 8 C MEMORY_END_ADDR $end
$var parameter 8 D MEMORY_STRT_ADDR $end
$var parameter 8 E UART_RX_ADDR $end
$var parameter 8 F UART_TX_ADDR $end
$var parameter 32 G WIDTH $end
$var reg 8 H PADDR [7:0] $end
$var reg 1 . PENABLE $end
$var reg 1 I PERIPHERAL_INDEX $end
$var reg 2 J PSEL [1:0] $end
$var reg 8 K PWDATA [7:0] $end
$var reg 1 ( PWRITE $end
$var reg 8 L data_r [7:0] $end
$var reg 1 " error $end
$var reg 1 ! ready $end
$var reg 2 M state [1:0] $end
$upscope $end
$scope module dut2 $end
$var wire 1 0 ENABLE_DMA $end
$var wire 8 N PADDR [7:0] $end
$var wire 1 ; PCLK $end
$var wire 1 . PENABLE $end
$var wire 1 O PSEL $end
$var wire 8 P PWDATA [7:0] $end
$var wire 1 ( PWRITE $end
$var wire 8 Q data_r [7:0] $end
$var wire 1 : error $end
$var wire 1 < ready $end
$var reg 8 R PRDATA [7:0] $end
$var reg 1 S PREADY $end
$var reg 1 T PSLVERR $end
$var reg 8 U addr [7:0] $end
$var reg 8 V data_w [7:0] $end
$var reg 1 $ dir $end
$var reg 1 # enable $end
$var reg 2 W state [1:0] $end
$upscope $end
$upscope $end
$enddefinitions $end
$comment Show the parameter values. $end
$dumpall
b111 G
b10000000 F
b10000001 E
b0 D
b1111111 C
$end
#0
$dumpvars
bx W
bx V
bx U
xT
1S
bx R
bz Q
bx P
xO
bx N
bx M
bx L
bx K
bx J
xI
bx H
bx B
bz A
bx @
bzx ?
bz1 >
bx =
1<
0;
0:
09
x8
bx 7
bz 6
bx 5
b1100111 4
bx 3
bz 2
bx 1
00
bx /
x.
bx -
bz1 ,
bx +
bzx *
bx )
x(
bx '
bx &
bx %
x$
0#
x"
x!
$end
#1
1;
#2
0;
#3
1;
#4
0;
#5
0O
bz &
bz L
0"
bz /
bz H
bz N
bz )
bz K
bz P
z(
b0 +
b0 J
b0 M
bz0 *
bz0 ?
0T
bz -
bz B
bz R
z$
bz %
bz V
bz '
bz U
b0 W
1;
10
#6
0.
b1100111 /
b1100111 H
b1100111 N
b1100111 )
b1100111 K
b1100111 P
1(
0!
1O
0I
b1 +
b1 J
0;
19
18
b1100111 1
b1100111 @
b1100111 6
b1100111 A
b1 =
b1100111 5
#7
bz0 ,
bz0 >
0S
0<
1#
b1100111 %
b1100111 V
b1 W
1.
b1 M
1;
#8
0;
#9
b10 M
b10 W
1$
b1100111 '
b1100111 U
1;
#10
0;
#11
1;
#12
bz1 ,
bz1 >
1S
0#
0;
b1100111 7
1<
#13
bz 1
bz @
z8
09
0O
0.
b0 +
b0 J
b0 M
1!
z(
bz /
bz H
bz N
bz )
bz K
bz P
b0 W
1;
#14
0;
#15
1;
#16
0;
#17
1;
#18
0;
#19
1;
#20
0;
#21
1;
#22
b1100111 /
b1100111 H
b1100111 N
b1000011 )
b1000011 K
b1000011 P
1(
0!
1O
b1 +
b1 J
0;
19
18
b1100111 1
b1100111 @
b1000011 6
b1000011 A
b0 =
b1000011 5
#23
b1000011 7
1#
b1000011 %
b1000011 V
b1 W
1.
b1 M
1;
#24
0;
#25
b10 M
b10 W
1;
#26
0;
#27
bz 1
bz @
z8
09
0O
b0 W
0#
0.
b0 +
b0 J
b0 M
1!
z(
bz /
bz H
bz N
bz )
bz K
bz P
1;
#28
0;
#29
1;
#30
0;
#31
1;
#32
0;
#33
1;
#34
0;
#35
1;
#36
0;
#37
1;
#38
0;
#39
1;
#40
0;
#41
1;
#42
b1100111 /
b1100111 H
b1100111 N
0(
0!
1O
b1 +
b1 J
0;
19
08
b1100111 1
b1100111 @
b1 =
#43
bz0 ,
bz0 >
0S
0<
1#
b1 W
1.
b1 M
1;
#44
0;
#45
b10 M
b10 W
0$
1;
#46
0;
#47
1;
#48
bz1 ,
bz1 >
1S
0#
0;
b1100111 2
b1100111 Q
1<
#49
bz 3
bz 1
bz @
z8
09
0O
0.
b0 +
b0 J
b0 M
1!
z(
bz /
bz H
bz N
b0 W
b1100111 -
b1100111 B
b1100111 R
1;
#50
0;
#51
bz -
bz B
bz R
1;
#52
0;
#53
1;
#54
0;
#55
1;
#56
0;
#57
1;
#58
b1100111 /
b1100111 H
b1100111 N
0(
0!
1O
b1 +
b1 J
0;
19
08
b1100111 1
b1100111 @
b0 =
b1000011 4
#59
b1000011 2
b1000011 Q
1#
b1 W
1.
b1 M
1;
#60
0;
#61
b10 M
b10 W
1;
#62
0;
#63
bz 1
bz @
z8
09
0O
b0 W
0#
b1000011 -
b1000011 B
b1000011 R
0.
b0 +
b0 J
b0 M
1!
z(
bz /
bz H
bz N
1;
#64
0;
#65
bz -
bz B
bz R
1;
