APB/APB_completer.v



// APB completer module

module APB_completer(

		input reg PCLK, //clock signal

		input reg ENABLE_DMA,	// to initialize state variable and other signals

	// ports to memory manager
		output reg enable,	// enable for mem manager, forwards PENABLE
		input reg ready,	// ready driven by mem manager, forwarded to PREADY
		output reg[7:0] addr,	// address bus for mem manager
		output reg[7:0] data_w,	// data write bus for mem manager
		input reg[7:0] data_r,	// data read bus
		output reg dir,		// r/w signal
		input reg error,	// error signal from mem manager


	// buses and signals to requester, APB
		input reg[7:0] PWDATA,  // data write bus (incoming)
		output reg[7:0] PRDATA, // data read bus(outgoing)
		input reg[7:0] PADDR, 	// address bus
		input reg PSEL, 	// select line for this peripheral
		input reg PWRITE, 	// r/w control line, write=1, read=0
		input reg PENABLE, 	// enable signal for APB r/w
		output reg PREADY,	// ready signal		
		output reg PSLVERR	// signals error when invalid addr or restricted r/w


);


reg[1:0] state; // state variable for FSM


// initializing state variable and other buses and signals.
always @(posedge ENABLE_DMA)
begin
	
	state <= 2'b00;

	enable <= 0;
	addr <= 8'bz;
	data_w <= 8'bz;
	dir <= 1'bz;
	PRDATA <= 8'bz;
	//PREADY <= 0;
	PSLVERR <= 0;

end


// enable ready logic
always @(posedge ready)
begin
	enable <= 0;
end




// APB completer FSM
always @(posedge PCLK)
begin
	
	case(state)
		
		2'b00 : begin
			//PREADY <= 0;
			PRDATA <= 8'bz;
			PSLVERR <= 0;
			if(PSEL==1)
				begin
				state <= 2'b01;
				end
			if(PWRITE==1)
				begin
				data_w <= PWDATA;
				end
			end
		
		2'b01 : begin

				addr <= PADDR;
				dir <= PWRITE;

				state <= 2'b10;

			end

		2'b10 : begin
			if(ready==1 || error==1)
				begin
				case(PWRITE)
	
					0 : begin
						PRDATA <= data_r;
					    end

				endcase
	
				PREADY <= 1;
				enable <= 0;
				state <= 2'b00;
				PSLVERR <= error;
				end
			end


	endcase

end


always @(posedge PENABLE)
begin
	enable <= 1;
end

always @(ready)
begin
	PREADY <= ready;
end



endmodule

APB/APB_requester.v



// APB interface module
module APB_requester(

	input reg PCLK,	// clock signal

	input reg ENABLE_DMA,	// to initialize state variable, buses and signals

// ports for master peripheral (here master is DMA)
	input reg[7:0] data_w, 	// data to write to the peripheral
	output reg[7:0] data_r, // data read from the peripheral
	input reg[7:0] addr, 	// address of memory or register to r/w data
	input reg dir,		// direction of data transfer write=1, read=0
	output reg error,	// error signal for invalid address or direction
	input reg enable,	// enable signal to begin transfer, initialize state variable, masterclock gating
	output reg ready, 	// signals the completion of transfer

// APB buses and control signals
	output reg[7:0] PWDATA, // data write bus
	input reg[7:0] PRDATA,  // data read bus
	output reg[7:0] PADDR,	 // address bus
	output reg[1:0] PSEL,	 // select lines, 1 for each peripheral. here, PSEL[1] for UART and PSEL[0] for memory
	output reg PWRITE,	 // read/write control line, write=1, read=0
	output reg PENABLE, 	 // enable signal for APB
	input reg[1:0] PREADY,	 // ready signals, PREADY[1] for UART and PREADY[0] for memory
	input reg[1:0] PSLVERR		// error response, used to indicate invalid address or direction.
);



// MEMORY_X_ADDR => memory address range
// UART_X_ADDR => UART TX and RX reg addresses
parameter MEMORY_STRT_ADDR = 8'h00, MEMORY_END_ADDR = 8'h7f, UART_TX_ADDR = 8'h80, UART_RX_ADDR = 8'h81, WIDTH = 7;



reg[1:0] state; //state variable
reg PERIPHERAL_INDEX; // used as index for PREADY and PSLVERR


// initializing state variable on ENABLE_DMA, DMA is enabled once and not disabled even if TXI or RXI is raised
always @(posedge ENABLE_DMA)
begin
	state <= 2'b00;
	PSEL <= 2'b00;
	PWRITE <= 1'bz;
	PWDATA <= 8'bz;
	PADDR <= 8'bz;
	error <= 0;
	data_r <= 8'bz;
end


// On positive edge of enable, ready pulled LOW, PWRITE initialized, data_x written to the PXDATA, addr written to PADDR
always @(posedge enable)
begin
	error <= 0;
	ready <= 0;
	PWRITE <= dir; 	// setting PWRITE
	
	// setting data bus according to dir input by master peripheral.
	case(dir)
		1 : PWDATA <= data_w;
	endcase
	PADDR <= addr;
	PENABLE <= 0;

end


// On posedge of enable, drive PSELx to HIGH based on the addr, ie. address to PSEL mapping and initializing PERIPHERAL_INDEX to be used as index in the FSM.
always @(posedge enable)
begin
	if(addr[WIDTH:0] >= MEMORY_STRT_ADDR && addr[WIDTH:0] <= MEMORY_END_ADDR)
	begin
		PSEL[0] = 1;
		PERIPHERAL_INDEX = 1'b0;
	end

	else if(addr == UART_RX_ADDR || addr == UART_TX_ADDR)
	begin
		PSEL[1] = 1;
		PERIPHERAL_INDEX = 1'b1;
	end
end



// FSM
always @(posedge PCLK)
begin
	
	case(state)
		2'b00 : begin
			
			if(PSEL[1:0] != 2'b00)
				begin
				state <= 2'b01;
				PENABLE <= 1;
				end
			end

		// SETUP
		2'b01 : begin
			//PENABLE <= 1;
			state <= 2'b10;
			end

		// ACCESS
		2'b10 : begin

			// for optional wait state
			if(PREADY[PERIPHERAL_INDEX]==1)
				begin
				// checks only the specific line to the selected peripheral
				case({PREADY[PERIPHERAL_INDEX], PSLVERR[PERIPHERAL_INDEX]})
				2'b10 : begin
				
					case(PWRITE)
						1 : begin
							// keeping data bus in high impedance after transfer
							PWDATA <= 8'bz;
						end

						0 : begin
							// reading data to data_r (giving to master peripheral)
							data_r <= PRDATA;
						end
					endcase
					// pulling addr bus and pwrite to high impedance after transfer is complete, also signalling 
					// transfer complete to master peripheral by pulling ready HIGH
					PADDR <= 8'bz;
					PWRITE <= 1'bz;
					ready <= 1;
					state <= 2'b00;
					PSEL <= 2'b00;
					PENABLE <= 0;
					PADDR <= 8'bz;
					PWDATA <= 8'bz;
					end

				// error HIGH, forwards to master and goes to state 00
				2'b11 : begin 
						state <= 2'b00;
						PSEL <= 2'b00;
						PENABLE <= 0;
						ready <= 1;
						error <= 1; // propogated to the CPU
						PADDR <= 8'bz;
						PWDATA <= 8'bz;
						PWRITE <= 1'bz;
					end

				// remains in ACCESS state
				2'b0x : begin
					state <= 2'b10;
					end
				endcase
				end
				
			end

	endcase

end




endmodule

APB/testbenches/APB_req_comp_tb.v



module APB_req_comp_tb;


reg ENABLE_DMA;
reg master_clk;	// PCLK


// APB BUS
wire[7:0] PWDATA;
wire [7:0] PADDR;
wire [1:0] PSEL;
wire PWRITE;
wire PENABLE;
wire[7:0] PRDATA;
wire[1:0] PREADY;
wire[1:0] PSLVERR;





// inputs to dut1 requester
reg[7:0] data_w_req;
reg[7:0] addr_req;
reg dir_req;
reg enable_req;


// outputs from dut1 requester
wire[7:0] data_r_req;
wire error_req;
wire ready_req;



// inputs to dut2 completer
reg[7:0] data_r_comp;
reg ready_comp;
reg error_comp;


//outputs from dut2 completer
wire[7:0] addr_comp;
wire dir_comp;
wire enable_comp;
wire[7:0] data_w_comp;



integer test_with_wait_state; // to indicate whether test is done with or without wait state

// TEST DATA FOR EACH TEST
parameter TEST_DATA_WRITE_WITHOUT_WW = 8'h76, TEST_DATA_WRITE_WITH_WW = 8'h67, TEST_DATA_READ_WITHOUT_WW = 8'h76, TEST_DATA_READ_WITH_WW = 8'h67;


// 8'h00 is the only accepted address that does not raise error signal in this testbench module
parameter TEST_ADDR_WRITE_WITHOUT_WW = 8'h00, TEST_ADDR_WRITE_WITH_WW = 8'h00, TEST_ADDR_READ_WITHOUT_WW = 8'h00, TEST_ADDR_READ_WITH_WW = 8'h00;


// address that does not raise error in this testbench module, 
parameter VALID_ADDR = 8'h00;	// must be valid with the requester module parameters



reg[7:0] data_to_write; // from requester
reg[7:0] data_written; // to completer

reg[7:0] data_to_read;  // from completer
reg[7:0] data_read; 	// to requester



APB_requester dut1(.PCLK(master_clk), .ENABLE_DMA(ENABLE_DMA), .data_w(data_w_req), .data_r(data_r_req), .addr(addr_req), .dir(dir_req), .error(error_req), .enable(enable_req), .ready(ready_req), .PWDATA(PWDATA), .PRDATA(PRDATA), .PADDR(PADDR), .PSEL(PSEL), .PWRITE(PWRITE), .PENABLE(PENABLE), .PREADY(PREADY), .PSLVERR(PSLVERR));



APB_completer dut2(.PCLK(master_clk), .ENABLE_DMA(ENABLE_DMA), .data_w(data_w_comp), .data_r(data_r_comp), .addr(addr_comp), .dir(dir_comp), .error(error_comp), .enable(enable_comp), .ready(ready_comp), .PWDATA(PWDATA), .PRDATA(PRDATA), .PADDR(PADDR), .PSEL(PSEL[0]), .PWRITE(PWRITE), .PENABLE(PENABLE), .PREADY(PREADY[0]), .PSLVERR(PSLVERR[0]));



//ready for requester side
always @(posedge ready_req)
begin
	enable_req <= 0;
	dir_req <= 1'bz;
	addr_req <= 8'bz;

	if(dir_req==0)
	data_read <= data_r_req;

end

always @(posedge enable_comp)
begin
	if(test_with_wait_state==0)
		begin
		if(dir_comp==0)
		begin
			if(addr_comp!=VALID_ADDR)
				error_comp = 1;
			else
				data_r_comp = data_to_read;

		end
		else
		begin
			if(addr_comp!=VALID_ADDR)
				error_comp = 1;
			else
				data_written = data_w_comp;
		end
		end
	else
		begin
		ready_comp = 0;
		#5;
		ready_comp = 1;
		if(dir_comp==0)
		begin
			if(addr_comp!=VALID_ADDR)
				error_comp = 1;
			else
				data_r_comp = data_to_read;
		end
		else
		begin
			if(addr_comp!=VALID_ADDR)
				error_comp = 1;
			else
				data_written = data_w_comp;
		end
		end
	
end



always #1 master_clk = ~master_clk;

initial begin
$dumpfile("APB.vcd");
$dumpvars();



ready_comp = 1;
error_comp = 0;


data_w_req = 8'bz;

data_r_comp = 8'bz;



master_clk = 0;

enable_req = 0;

ENABLE_DMA = 0;
#5;
ENABLE_DMA = 1;
#1;


data_to_write = TEST_DATA_WRITE_WITH_WW;
// testing write operation with wait state.
test_with_wait_state = 1;
data_w_req = data_to_write;
addr_req = 8'h00;
dir_req = 1;
enable_req = 1;
#16;
error_comp = 0;

data_to_write = TEST_DATA_WRITE_WITHOUT_WW;
// testing write operation without wait state
test_with_wait_state = 0;
data_w_req = data_to_write;
addr_req = 8'h00;
dir_req = 1;
enable_req = 1;
#20;
error_comp = 0;

data_to_read = TEST_DATA_READ_WITH_WW;
// testing read operation with wait state
test_with_wait_state = 1;
//data_w_req = data_to_write;
addr_req = 8'h00;
dir_req = 0;
enable_req = 1;
#16;
error_comp = 0;

data_to_read = TEST_DATA_READ_WITHOUT_WW;
// testing write operation without wait state
test_with_wait_state = 0;
//data_w_req = data_to_write;
addr_req = 8'h00;
dir_req = 0;
enable_req = 1;
#16;
error_comp = 0;


$finish;
end


endmodule

APB/VCD/APB.vcd
$date
	Tue Jun  9 16:53:57 2026
$end
$version
	Icarus Verilog
$end
$timescale
	1s
$end
$scope module APB_req_comp_tb $end
$var wire 1 ! ready_req $end
$var wire 1 " error_req $end
$var wire 1 # enable_comp $end
$var wire 1 $ dir_comp $end
$var wire 8 % data_w_comp [7:0] $end
$var wire 8 & data_r_req [7:0] $end
$var wire 8 ' addr_comp [7:0] $end
$var wire 1 ( PWRITE $end
$var wire 8 ) PWDATA [7:0] $end
$var wire 2 * PSLVERR [1:0] $end
$var wire 2 + PSEL [1:0] $end
$var wire 2 , PREADY [1:0] $end
$var wire 8 - PRDATA [7:0] $end
$var wire 1 . PENABLE $end
$var wire 8 / PADDR [7:0] $end
$var parameter 8 0 TEST_ADDR_READ_WITHOUT_WW $end
$var parameter 8 1 TEST_ADDR_READ_WITH_WW $end
$var parameter 8 2 TEST_ADDR_WRITE_WITHOUT_WW $end
$var parameter 8 3 TEST_ADDR_WRITE_WITH_WW $end
$var parameter 8 4 TEST_DATA_READ_WITHOUT_WW $end
$var parameter 8 5 TEST_DATA_READ_WITH_WW $end
$var parameter 8 6 TEST_DATA_WRITE_WITHOUT_WW $end
$var parameter 8 7 TEST_DATA_WRITE_WITH_WW $end
$var parameter 8 8 VALID_ADDR $end
$var reg 1 9 ENABLE_DMA $end
$var reg 8 : addr_req [7:0] $end
$var reg 8 ; data_r_comp [7:0] $end
$var reg 8 < data_read [7:0] $end
$var reg 8 = data_to_read [7:0] $end
$var reg 8 > data_to_write [7:0] $end
$var reg 8 ? data_w_req [7:0] $end
$var reg 8 @ data_written [7:0] $end
$var reg 1 A dir_req $end
$var reg 1 B enable_req $end
$var reg 1 C error_comp $end
$var reg 1 D master_clk $end
$var reg 1 E ready_comp $end
$var integer 32 F test_with_wait_state [31:0] $end
$scope module dut1 $end
$var wire 1 9 ENABLE_DMA $end
$var wire 1 D PCLK $end
$var wire 2 G PREADY [1:0] $end
$var wire 2 H PSLVERR [1:0] $end
$var wire 8 I addr [7:0] $end
$var wire 8 J data_w [7:0] $end
$var wire 1 A dir $end
$var wire 1 B enable $end
$var wire 8 K PRDATA [7:0] $end
$var parameter 8 L MEMORY_END_ADDR $end
$var parameter 8 M MEMORY_STRT_ADDR $end
$var parameter 8 N UART_RX_ADDR $end
$var parameter 8 O UART_TX_ADDR $end
$var parameter 32 P WIDTH $end
$var reg 8 Q PADDR [7:0] $end
$var reg 1 . PENABLE $end
$var reg 1 R PERIPHERAL_INDEX $end
$var reg 2 S PSEL [1:0] $end
$var reg 8 T PWDATA [7:0] $end
$var reg 1 ( PWRITE $end
$var reg 8 U data_r [7:0] $end
$var reg 1 " error $end
$var reg 1 ! ready $end
$var reg 2 V state [1:0] $end
$upscope $end
$scope module dut2 $end
$var wire 1 9 ENABLE_DMA $end
$var wire 8 W PADDR [7:0] $end
$var wire 1 D PCLK $end
$var wire 1 . PENABLE $end
$var wire 1 X PSEL $end
$var wire 8 Y PWDATA [7:0] $end
$var wire 1 ( PWRITE $end
$var wire 8 Z data_r [7:0] $end
$var wire 1 C error $end
$var wire 1 E ready $end
$var reg 8 [ PRDATA [7:0] $end
$var reg 1 \ PREADY $end
$var reg 1 ] PSLVERR $end
$var reg 8 ^ addr [7:0] $end
$var reg 8 _ data_w [7:0] $end
$var reg 1 $ dir $end
$var reg 1 # enable $end
$var reg 2 ` state [1:0] $end
$upscope $end
$upscope $end
$enddefinitions $end
$comment Show the parameter values. $end
$dumpall
b111 P
b10000000 O
b10000001 N
b0 M
b1111111 L
b0 8
b1100111 7
b1110110 6
b1100111 5
b1110110 4
b0 3
b0 2
b0 1
b0 0
$end
#0
$dumpvars
bx `
bx _
bx ^
x]
1\
bx [
bz Z
bx Y
xX
bx W
bx V
bx U
bx T
bx S
xR
bx Q
bx K
bz J
bx I
bzx H
bz1 G
bx F
1E
0D
0C
0B
xA
bx @
bz ?
bx >
bx =
bx <
bz ;
bx :
09
bx /
x.
bx -
bz1 ,
bx +
bzx *
bx )
x(
bx '
bx &
bx %
x$
0#
x"
x!
$end
#1
1D
#2
0D
#3
1D
#4
0D
#5
0X
bz &
bz U
0"
bz /
bz Q
bz W
bz )
bz T
bz Y
z(
b0 +
b0 S
b0 V
bz0 *
bz0 H
0]
bz -
bz K
bz [
z$
bz %
bz _
bz '
bz ^
b0 `
1D
19
#6
bz0 ,
bz0 G
0\
0.
b0 /
b0 Q
b0 W
b1100111 )
b1100111 T
b1100111 Y
1(
0!
1X
0R
b1 +
b1 S
0D
1B
1A
b0 :
b0 I
b1100111 ?
b1100111 J
b1 F
b1100111 >
#7
0E
1.
b10 V
b1 `
1#
b1100111 %
b1100111 _
1$
b0 '
b0 ^
1D
#8
0D
#9
1D
#10
0D
#11
1D
#12
bz1 ,
bz1 G
1\
0#
0D
b1100111 @
1E
#13
bz0 ,
bz0 G
0\
bz :
bz I
zA
0B
0X
0.
b0 +
b0 S
b0 V
1!
z(
bz /
bz Q
bz W
bz )
bz T
bz Y
b10 `
1D
#14
0D
#15
b0 `
1D
#16
0D
#17
1D
#18
0D
#19
1D
#20
0D
#21
1D
#22
b0 /
b0 Q
b0 W
b1110110 )
b1110110 T
b1110110 Y
1(
0!
1X
b1 +
b1 S
0D
1B
1A
b0 :
b0 I
b1110110 ?
b1110110 J
b0 F
b1110110 >
#23
bz1 ,
bz1 G
1\
b1110110 @
1.
b10 V
b1 `
1#
b1110110 %
b1110110 _
1D
#24
0D
#25
bz0 ,
bz0 G
0\
bz :
bz I
zA
0B
0X
0.
b0 +
b0 S
b0 V
1!
z(
bz /
bz Q
bz W
bz )
bz T
bz Y
b10 `
1D
#26
0D
#27
b0 `
0#
1D
#28
0D
#29
1D
#30
0D
#31
1D
#32
0D
#33
1D
#34
0D
#35
1D
#36
0D
#37
1D
#38
0D
#39
1D
#40
0D
#41
1D
#42
b0 /
b0 Q
b0 W
0(
0!
1X
b1 +
b1 S
0D
1B
0A
b0 :
b0 I
b1 F
b1100111 =
#43
0E
1.
b10 V
b1 `
1#
0$
1D
#44
0D
#45
1D
#46
0D
#47
1D
#48
b1100111 -
b1100111 K
b1100111 [
bz1 ,
bz1 G
1\
0#
0D
b1100111 ;
b1100111 Z
1E
#49
bz0 ,
bz0 G
0\
b1100111 <
bz :
bz I
zA
0B
0X
0.
b0 +
b0 S
b0 V
1!
z(
bz /
bz Q
bz W
b1100111 &
b1100111 U
b10 `
1D
#50
0D
#51
b0 `
1D
#52
0D
#53
1D
#54
0D
#55
1D
#56
0D
#57
1D
#58
b0 /
b0 Q
b0 W
0(
0!
1X
b1 +
b1 S
0D
1B
0A
b0 :
b0 I
b0 F
b1110110 =
#59
b1110110 -
b1110110 K
b1110110 [
bz1 ,
bz1 G
1\
b1110110 ;
b1110110 Z
1.
b10 V
b1 `
1#
1D
#60
0D
#61
bz0 ,
bz0 G
0\
b1110110 <
bz :
bz I
zA
0B
0X
0.
b0 +
b0 S
b0 V
1!
z(
bz /
bz Q
bz W
b1110110 &
b1110110 U
b10 `
1D
#62
0D
#63
b0 `
0#
1D
