APB/APB_requester.v



// APB interface module
module APB_requester(

	input reg PCLK,	// clock signal

	input reg ENABLE_DMA,	// to initialize state variable, buses and signals

// ports for master peripheral (here master is DMA)
	input reg[7:0] data_w, 	// data to write to the peripheral
	output reg[7:0] data_r, // data read from the peripheral
	input reg[7:0] addr, 	// address of memory or register to r/w data
	input reg dir,		// direction of data transfer write=1, read=0
	output reg error,	// error signal for invalid address or direction
	input reg enable,	// enable signal to begin transfer, initialize state variable, masterclock gating
	output reg ready, 	// signals the completion of transfer

// APB buses and control signals
	output reg[7:0] PWDATA, // data write bus
	input reg[7:0] PRDATA,  // data read bus
	output reg[7:0] PADDR,	 // address bus
	output reg[1:0] PSEL,	 // select lines, 1 for each peripheral. here, PSEL[1] for UART and PSEL[0] for memory
	output reg PWRITE,	 // read/write control line, write=1, read=0
	output reg PENABLE, 	 // enable signal for APB
	input reg[1:0] PREADY,	 // ready signals, PREADY[1] for UART and PREADY[0] for memory
	input reg[1:0] PSLVERR		// error response, used to indicate invalid address or direction.
);



// MEMORY_X_ADDR => memory address range
// UART_X_ADDR => UART TX and RX reg addresses
parameter MEMORY_STRT_ADDR = 8'h00, MEMORY_END_ADDR = 8'h7f, UART_TX_ADDR = 8'h80, UART_RX_ADDR = 8'h81, WIDTH = 7;



reg[1:0] state; //state variable
reg PERIPHERAL_INDEX; // used as index for PREADY and PSLVERR


// initializing state variable on ENABLE_DMA, DMA is enabled once and not disabled even if TXI or RXI is raised
always @(posedge ENABLE_DMA)
begin
	state <= 2'b00;
	PSEL <= 2'b00;
	PWRITE <= 1'bz;
	PWDATA <= 8'bz;
	PADDR <= 8'bz;
	error <= 0;
	data_r <= 8'bz;
end


// On positive edge of enable, ready pulled LOW, PWRITE initialized, data_x written to the PXDATA, addr written to PADDR
always @(posedge enable)
begin
	error <= 0;
	ready <= 0;
	PWRITE <= dir; 	// setting PWRITE
	
	// setting data bus according to dir input by master peripheral.
	case(dir)
		1 : PWDATA <= data_w;
	endcase
	PADDR <= addr;
	PENABLE <= 0;

end


// On posedge of enable, drive PSELx to HIGH based on the addr, ie. address to PSEL mapping and initializing PERIPHERAL_INDEX to be used as index in the FSM.
always @(posedge enable)
begin
	if(addr[WIDTH:0] >= MEMORY_STRT_ADDR && addr[WIDTH:0] <= MEMORY_END_ADDR)
	begin
		PSEL[0] = 1;
		PERIPHERAL_INDEX = 1'b0;
	end

	else if(addr == UART_RX_ADDR || addr == UART_TX_ADDR)
	begin
		PSEL[1] = 1;
		PERIPHERAL_INDEX = 1'b1;
	end
end



// FSM
always @(posedge PCLK)
begin
	
	case(state)
		2'b00 : begin
			
			if(PSEL[1:0] != 2'b00)
				begin
				state <= 2'b01;
				PENABLE <= 1;
				end
			end

		// SETUP
		2'b01 : begin
			//PENABLE <= 1;
			state <= 2'b10;
			end

		// ACCESS
		2'b10 : begin

			// for optional wait state
			if(PREADY[PERIPHERAL_INDEX]==1)
				begin
				// checks only the specific line to the selected peripheral
				case({PREADY[PERIPHERAL_INDEX], PSLVERR[PERIPHERAL_INDEX]})
				2'b10 : begin
				
					case(PWRITE)
						1 : begin
							// keeping data bus in high impedance after transfer
							PWDATA <= 8'bz;
						end

						0 : begin
							// reading data to data_r (giving to master peripheral)
							data_r <= PRDATA;
						end
					endcase
					// pulling addr bus and pwrite to high impedance after transfer is complete, also signalling 
					// transfer complete to master peripheral by pulling ready HIGH
					PADDR <= 8'bz;
					PWRITE <= 1'bz;
					ready <= 1;
					state <= 2'b00;
					PSEL <= 2'b00;
					PENABLE <= 0;
					PADDR <= 8'bz;
					PWDATA <= 8'bz;
					end

				// error HIGH, forwards to master and goes to state 00
				2'b11 : begin 
						state <= 2'b00;
						PSEL <= 2'b00;
						PENABLE <= 0;
						ready <= 1;
						error <= 1; // propogated to the CPU
						PADDR <= 8'bz;
						PWDATA <= 8'bz;
						PWRITE <= 1'bz;
					end

				// remains in ACCESS state
				2'b0x : begin
					state <= 2'b10;
					end
				endcase
				end
				
			end

	endcase

end




endmodule

APB/testbenches/APB_requester_tb.v


// APB_requester testbench

module APB_requester_tb;



// inputs to dut
reg ENABLE_DMA;
reg master_clk;		// functions as PCLK
reg[7:0] data_w;
reg[7:0] addr;
reg dir;
reg enable;
reg[7:0] PRDATA;
reg[1:0] PREADY;
reg[1:0] PSLVERR;

// outputs from dut
wire[7:0] data_r;
wire error;
wire ready;
wire[7:0] PWDATA;
wire [7:0] PADDR;
wire [1:0] PSEL;
wire PWRITE;
wire PENABLE;

reg[7:0] write_data;
reg[7:0] read_data;


APB_requester dut(.PCLK(master_clk), .ENABLE_DMA(ENABLE_DMA), .data_w(data_w), .data_r(data_r), .addr(addr), .dir(dir), .error(error), .enable(enable), .ready(ready), .PWDATA(PWDATA), .PRDATA(PRDATA), .PADDR(PADDR), .PSEL(PSEL), .PWRITE(PWRITE), .PENABLE(PENABLE), .PREADY(PREADY), .PSLVERR(PSLVERR));

integer op;

always @(posedge PENABLE)
begin
// Peripheral side
if(PSEL[0]==1)
	begin

	// WRITE operation
	if(PWRITE==1 && PENABLE==1)
		begin
		PREADY[0] = 1;
		write_data = PWDATA;
		op = 1;
		end

	// READ operation
	if(PWRITE==0 && PENABLE==1)
		begin
		PREADY[0] = 1;
		PRDATA <= read_data;
		end

	end
end


always @(posedge ready)
begin
	enable <= 0;

end





always #1 master_clk = ~master_clk;

initial begin

$dumpfile("APB_requester.vcd");
$dumpvars();

enable = 0;
op = 0;

master_clk = 0;
ENABLE_DMA = 0;
PREADY = 2'b00;
PSLVERR = 2'b00;

#3;
ENABLE_DMA = 1;
#10;

// testing write operation
data_w = 8'h67;
addr = 8'h10;
dir = 1;
#2;
enable = 1;
#30;
PREADY[0] = 0;



// testing read operation
read_data = 8'h59;
addr = 8'h01;
dir = 0;
#2;
enable = 1;


#50;
$finish;

end

endmodule

APB/VCD/APB_requester.vcd
$date
	Mon Jun  8 23:09:47 2026
$end
$version
	Icarus Verilog
$end
$timescale
	1s
$end
$scope module APB_requester_tb $end
$var wire 1 ! ready $end
$var wire 1 " error $end
$var wire 8 # data_r [7:0] $end
$var wire 1 $ PWRITE $end
$var wire 8 % PWDATA [7:0] $end
$var wire 2 & PSEL [1:0] $end
$var wire 1 ' PENABLE $end
$var wire 8 ( PADDR [7:0] $end
$var reg 1 ) ENABLE_DMA $end
$var reg 8 * PRDATA [7:0] $end
$var reg 2 + PREADY [1:0] $end
$var reg 2 , PSLVERR [1:0] $end
$var reg 8 - addr [7:0] $end
$var reg 8 . data_w [7:0] $end
$var reg 1 / dir $end
$var reg 1 0 enable $end
$var reg 1 1 master_clk $end
$var reg 8 2 read_data [7:0] $end
$var reg 8 3 write_data [7:0] $end
$var integer 32 4 op [31:0] $end
$scope module dut $end
$var wire 1 ) ENABLE_DMA $end
$var wire 1 1 PCLK $end
$var wire 8 5 PRDATA [7:0] $end
$var wire 2 6 PREADY [1:0] $end
$var wire 2 7 PSLVERR [1:0] $end
$var wire 8 8 addr [7:0] $end
$var wire 8 9 data_w [7:0] $end
$var wire 1 / dir $end
$var wire 1 0 enable $end
$var parameter 8 : MEMORY_END_ADDR $end
$var parameter 8 ; MEMORY_STRT_ADDR $end
$var parameter 8 < UART_RX_ADDR $end
$var parameter 8 = UART_TX_ADDR $end
$var parameter 32 > WIDTH $end
$var reg 8 ? PADDR [7:0] $end
$var reg 1 ' PENABLE $end
$var reg 1 @ PERIPHERAL_INDEX $end
$var reg 2 A PSEL [1:0] $end
$var reg 8 B PWDATA [7:0] $end
$var reg 1 $ PWRITE $end
$var reg 8 C data_r [7:0] $end
$var reg 1 " error $end
$var reg 1 ! ready $end
$var reg 2 D state [1:0] $end
$upscope $end
$upscope $end
$enddefinitions $end
$comment Show the parameter values. $end
$dumpall
b111 >
b10000000 =
b10000001 <
b0 ;
b1111111 :
$end
#0
$dumpvars
bx D
bx C
bx B
bx A
x@
bx ?
bx 9
bx 8
b0 7
b0 6
bx 5
b0 4
bx 3
bx 2
01
00
x/
bx .
bx -
b0 ,
b0 +
bx *
0)
bx (
x'
bx &
bx %
x$
bx #
x"
x!
$end
#1
11
#2
01
#3
0"
bz (
bz ?
bz %
bz B
z$
b0 &
b0 A
b0 D
11
1)
#4
01
#5
11
#6
01
#7
11
#8
01
#9
11
#10
01
#11
11
#12
01
#13
11
1/
b10000 -
b10000 8
b1100111 .
b1100111 9
#14
01
#15
b1 D
0'
b10000 (
b10000 ?
b1100111 %
b1100111 B
1$
0!
0@
b1 &
b1 A
11
10
#16
01
#17
b1 4
b1100111 3
b1 +
b1 6
b10 D
1'
11
#18
01
#19
00
0'
b0 &
b0 A
b0 D
1!
z$
bz (
bz ?
bz %
bz B
11
#20
01
#21
11
#22
01
#23
11
#24
01
#25
11
#26
01
#27
11
#28
01
#29
11
#30
01
#31
11
#32
01
#33
11
#34
01
#35
11
#36
01
#37
11
#38
01
#39
11
#40
01
#41
11
#42
01
#43
11
#44
01
#45
11
0/
b1 -
b1 8
b1011001 2
b0 +
b0 6
#46
01
#47
b1 D
b1 (
b1 ?
0$
0!
b1 &
b1 A
11
10
#48
01
#49
b1011001 *
b1011001 5
b1 +
b1 6
b10 D
1'
11
#50
01
#51
00
0'
b0 &
b0 A
b0 D
1!
z$
bz (
bz ?
b1011001 #
b1011001 C
11
