UART/modules/clk_divider.v
/*

problem : initialization of counter and uart_clk
solution : initialized on enabling of RE, TE


problem : RE, TE not enabled simultaneosly, so counter can get resetted without completing half uart_clk cycle
advantage : uart_clk is enabled only when user activates uart. This helps to reduce unwanted power dissipation

FAILED
solution : initializes counter and uart_clk only when any ONE of TE or RE is enabled, ie. the condition is not satisfied 
	   if they are enabled at different times hence counter will not get reset.
trade-off : Assumes TE or RE is disabled when uart usage is over, because if TE or RE is disabled at different times, the condition still satisfies and resets the counter.

KEEPING AS A TRADE OFF assuming that the user is not intending to start uart until both RE and TE are enabled.

*/


//divides master_clk by 32
module clk_divider(input reg master_clk,//master clock of 11.0592MHz
		   output reg uart_clk,	//divided clock for uart
		   input reg RE, 	// used to initialize uart_clk and counter when RE enabled
		   input reg TE 	// used to initialize uart_clk and counter when TE enabled
		);



reg[3:0] counter; //to count number of master_clk posedge
reg flag;

//initializing counter and uart_clk on enabling of RE or TE
always @(TE, RE)
begin

	counter <= 4'b1111; //loaded with 16
	uart_clk <= 0;

end


//main block that divides clock by 32
always @(posedge master_clk)
begin
	//decrements counter on every master_clk posedge
	if(counter!=4'b0)
		counter <= counter - 1;

	//when counter reaches 0, uart clock is inverted and also counter is loaded with d16 for next clock cycle
	if(counter==4'b0000)
	begin
		uart_clk <= ~uart_clk;
		counter <= 4'b1111;
	end
end

endmodule

UART/testbenches/clk_divider_tb.v



module clk_divider_tb;

reg master_clk;
wire uart_clk;
reg RE;
reg TE;


clk_divider C0(.master_clk(master_clk), .uart_clk(uart_clk), .RE(RE), .TE(TE));

always #1 master_clk = ~master_clk;

initial begin
$dumpfile("clk_divider.vcd");
$dumpvars();
master_clk = 0;

RE = 1;
#6;
TE = 1;

#640;

$finish;
end

endmodule

UART/VCD/clk_divider.vcd
$date
	Tue Jun  2 19:02:42 2026
$end
$version
	Icarus Verilog
$end
$timescale
	1s
$end
$scope module clk_divider_tb $end
$var wire 1 ! uart_clk $end
$var reg 1 " RE $end
$var reg 1 # TE $end
$var reg 1 $ master_clk $end
$scope module C0 $end
$var wire 1 " RE $end
$var wire 1 # TE $end
$var wire 1 $ master_clk $end
$var reg 4 % counter [3:0] $end
$var reg 1 ! uart_clk $end
$upscope $end
$upscope $end
$enddefinitions $end
$comment Show the parameter values. $end
$dumpall
$end
#0
$dumpvars
b1111 %
0$
x#
1"
0!
$end
#1
b1110 %
1$
#2
0$
#3
b1101 %
1$
#4
0$
#5
b1100 %
1$
#6
b1111 %
0$
1#
#7
b1110 %
1$
#8
0$
#9
b1101 %
1$
#10
0$
#11
b1100 %
1$
#12
0$
#13
b1011 %
1$
#14
0$
#15
b1010 %
1$
#16
0$
#17
b1001 %
1$
#18
0$
#19
b1000 %
1$
#20
0$
#21
b111 %
1$
#22
0$
#23
b110 %
1$
#24
0$
#25
b101 %
1$
#26
0$
#27
b100 %
1$
#28
0$
#29
b11 %
1$
#30
0$
#31
b10 %
1$
#32
0$
#33
b1 %
1$
#34
0$
#35
b0 %
1$
#36
0$
#37
b1111 %
1!
1$
#38
0$
#39
b1110 %
1$
#40
0$
#41
b1101 %
1$
#42
0$
#43
b1100 %
1$
#44
0$
#45
b1011 %
1$
#46
0$
#47
b1010 %
1$
#48
0$
#49
b1001 %
1$
#50
0$
#51
b1000 %
1$
#52
0$
#53
b111 %
1$
#54
0$
#55
b110 %
1$
#56
0$
#57
b101 %
1$
#58
0$
#59
b100 %
1$
#60
0$
#61
b11 %
1$
#62
0$
#63
b10 %
1$
#64
0$
#65
b1 %
1$
#66
0$
#67
b0 %
1$
#68
0$
#69
b1111 %
0!
1$
#70
0$
#71
b1110 %
1$
#72
0$
#73
b1101 %
1$
#74
0$
#75
b1100 %
1$
#76
0$
#77
b1011 %
1$
#78
0$
#79
b1010 %
1$
#80
0$
#81
b1001 %
1$
#82
0$
#83
b1000 %
1$
#84
0$
#85
b111 %
1$
#86
0$
#87
b110 %
1$
#88
0$
#89
b101 %
1$
#90
0$
#91
b100 %
1$
#92
0$
#93
b11 %
1$
#94
0$
#95
b10 %
1$
#96
0$
#97
b1 %
1$
#98
0$
#99
b0 %
1$
#100
0$
#101
b1111 %
1!
1$
#102
0$
#103
b1110 %
1$
#104
0$
#105
b1101 %
1$
#106
0$
#107
b1100 %
1$
#108
0$
#109
b1011 %
1$
#110
0$
#111
b1010 %
1$
#112
0$
#113
b1001 %
1$
#114
0$
#115
b1000 %
1$
#116
0$
#117
b111 %
1$
#118
0$
#119
b110 %
1$
#120
0$
#121
b101 %
1$
#122
0$
#123
b100 %
1$
#124
0$
#125
b11 %
1$
#126
0$
#127
b10 %
1$
#128
0$
#129
b1 %
1$
#130
0$
#131
b0 %
1$
#132
0$
#133
b1111 %
0!
1$
#134
0$
#135
b1110 %
1$
#136
0$
#137
b1101 %
1$
#138
0$
#139
b1100 %
1$
#140
0$
#141
b1011 %
1$
#142
0$
#143
b1010 %
1$
#144
0$
#145
b1001 %
1$
#146
0$
#147
b1000 %
1$
#148
0$
#149
b111 %
1$
#150
0$
#151
b110 %
1$
#152
0$
#153
b101 %
1$
#154
0$
#155
b100 %
1$
#156
0$
#157
b11 %
1$
#158
0$
#159
b10 %
1$
#160
0$
#161
b1 %
1$
#162
0$
#163
b0 %
1$
#164
0$
#165
b1111 %
1!
1$
#166
0$
#167
b1110 %
1$
#168
0$
#169
b1101 %
1$
#170
0$
#171
b1100 %
1$
#172
0$
#173
b1011 %
1$
#174
0$
#175
b1010 %
1$
#176
0$
#177
b1001 %
1$
#178
0$
#179
b1000 %
1$
#180
0$
#181
b111 %
1$
#182
0$
#183
b110 %
1$
#184
0$
#185
b101 %
1$
#186
0$
#187
b100 %
1$
#188
0$
#189
b11 %
1$
#190
0$
#191
b10 %
1$
#192
0$
#193
b1 %
1$
#194
0$
#195
b0 %
1$
#196
0$
#197
b1111 %
0!
1$
#198
0$
#199
b1110 %
1$
#200
0$
#201
b1101 %
1$
#202
0$
#203
b1100 %
1$
#204
0$
#205
b1011 %
1$
#206
0$
#207
b1010 %
1$
#208
0$
#209
b1001 %
1$
#210
0$
#211
b1000 %
1$
#212
0$
#213
b111 %
1$
#214
0$
#215
b110 %
1$
#216
0$
#217
b101 %
1$
#218
0$
#219
b100 %
1$
#220
0$
#221
b11 %
1$
#222
0$
#223
b10 %
1$
#224
0$
#225
b1 %
1$
#226
0$
#227
b0 %
1$
#228
0$
#229
b1111 %
1!
1$
#230
0$
#231
b1110 %
1$
#232
0$
#233
b1101 %
1$
#234
0$
#235
b1100 %
1$
#236
0$
#237
b1011 %
1$
#238
0$
#239
b1010 %
1$
#240
0$
#241
b1001 %
1$
#242
0$
#243
b1000 %
1$
#244
0$
#245
b111 %
1$
#246
0$
#247
b110 %
1$
#248
0$
#249
b101 %
1$
#250
0$
#251
b100 %
1$
#252
0$
#253
b11 %
1$
#254
0$
#255
b10 %
1$
#256
0$
#257
b1 %
1$
#258
0$
#259
b0 %
1$
#260
0$
#261
b1111 %
0!
1$
#262
0$
#263
b1110 %
1$
#264
0$
#265
b1101 %
1$
#266
0$
#267
b1100 %
1$
#268
0$
#269
b1011 %
1$
#270
0$
#271
b1010 %
1$
#272
0$
#273
b1001 %
1$
#274
0$
#275
b1000 %
1$
#276
0$
#277
b111 %
1$
#278
0$
#279
b110 %
1$
#280
0$
#281
b101 %
1$
#282
0$
#283
b100 %
1$
#284
0$
#285
b11 %
1$
#286
0$
#287
b10 %
1$
#288
0$
#289
b1 %
1$
#290
0$
#291
b0 %
1$
#292
0$
#293
b1111 %
1!
1$
#294
0$
#295
b1110 %
1$
#296
0$
#297
b1101 %
1$
#298
0$
#299
b1100 %
1$
#300
0$
#301
b1011 %
1$
#302
0$
#303
b1010 %
1$
#304
0$
#305
b1001 %
1$
#306
0$
#307
b1000 %
1$
#308
0$
#309
b111 %
1$
#310
0$
#311
b110 %
1$
#312
0$
#313
b101 %
1$
#314
0$
#315
b100 %
1$
#316
0$
#317
b11 %
1$
#318
0$
#319
b10 %
1$
#320
0$
#321
b1 %
1$
#322
0$
#323
b0 %
1$
#324
0$
#325
b1111 %
0!
1$
#326
0$
#327
b1110 %
1$
#328
0$
#329
b1101 %
1$
#330
0$
#331
b1100 %
1$
#332
0$
#333
b1011 %
1$
#334
0$
#335
b1010 %
1$
#336
0$
#337
b1001 %
1$
#338
0$
#339
b1000 %
1$
#340
0$
#341
b111 %
1$
#342
0$
#343
b110 %
1$
#344
0$
#345
b101 %
1$
#346
0$
#347
b100 %
1$
#348
0$
#349
b11 %
1$
#350
0$
#351
b10 %
1$
#352
0$
#353
b1 %
1$
#354
0$
#355
b0 %
1$
#356
0$
#357
b1111 %
1!
1$
#358
0$
#359
b1110 %
1$
#360
0$
#361
b1101 %
1$
#362
0$
#363
b1100 %
1$
#364
0$
#365
b1011 %
1$
#366
0$
#367
b1010 %
1$
#368
0$
#369
b1001 %
1$
#370
0$
#371
b1000 %
1$
#372
0$
#373
b111 %
1$
#374
0$
#375
b110 %
1$
#376
0$
#377
b101 %
1$
#378
0$
#379
b100 %
1$
#380
0$
#381
b11 %
1$
#382
0$
#383
b10 %
1$
#384
0$
#385
b1 %
1$
#386
0$
#387
b0 %
1$
#388
0$
#389
b1111 %
0!
1$
#390
0$
#391
b1110 %
1$
#392
0$
#393
b1101 %
1$
#394
0$
#395
b1100 %
1$
#396
0$
#397
b1011 %
1$
#398
0$
#399
b1010 %
1$
#400
0$
#401
b1001 %
1$
#402
0$
#403
b1000 %
1$
#404
0$
#405
b111 %
1$
#406
0$
#407
b110 %
1$
#408
0$
#409
b101 %
1$
#410
0$
#411
b100 %
1$
#412
0$
#413
b11 %
1$
#414
0$
#415
b10 %
1$
#416
0$
#417
b1 %
1$
#418
0$
#419
b0 %
1$
#420
0$
#421
b1111 %
1!
1$
#422
0$
#423
b1110 %
1$
#424
0$
#425
b1101 %
1$
#426
0$
#427
b1100 %
1$
#428
0$
#429
b1011 %
1$
#430
0$
#431
b1010 %
1$
#432
0$
#433
b1001 %
1$
#434
0$
#435
b1000 %
1$
#436
0$
#437
b111 %
1$
#438
0$
#439
b110 %
1$
#440
0$
#441
b101 %
1$
#442
0$
#443
b100 %
1$
#444
0$
#445
b11 %
1$
#446
0$
#447
b10 %
1$
#448
0$
#449
b1 %
1$
#450
0$
#451
b0 %
1$
#452
0$
#453
b1111 %
0!
1$
#454
0$
#455
b1110 %
1$
#456
0$
#457
b1101 %
1$
#458
0$
#459
b1100 %
1$
#460
0$
#461
b1011 %
1$
#462
0$
#463
b1010 %
1$
#464
0$
#465
b1001 %
1$
#466
0$
#467
b1000 %
1$
#468
0$
#469
b111 %
1$
#470
0$
#471
b110 %
1$
#472
0$
#473
b101 %
1$
#474
0$
#475
b100 %
1$
#476
0$
#477
b11 %
1$
#478
0$
#479
b10 %
1$
#480
0$
#481
b1 %
1$
#482
0$
#483
b0 %
1$
#484
0$
#485
b1111 %
1!
1$
#486
0$
#487
b1110 %
1$
#488
0$
#489
b1101 %
1$
#490
0$
#491
b1100 %
1$
#492
0$
#493
b1011 %
1$
#494
0$
#495
b1010 %
1$
#496
0$
#497
b1001 %
1$
#498
0$
#499
b1000 %
1$
#500
0$
#501
b111 %
1$
#502
0$
#503
b110 %
1$
#504
0$
#505
b101 %
1$
#506
0$
#507
b100 %
1$
#508
0$
#509
b11 %
1$
#510
0$
#511
b10 %
1$
#512
0$
#513
b1 %
1$
#514
0$
#515
b0 %
1$
#516
0$
#517
b1111 %
0!
1$
#518
0$
#519
b1110 %
1$
#520
0$
#521
b1101 %
1$
#522
0$
#523
b1100 %
1$
#524
0$
#525
b1011 %
1$
#526
0$
#527
b1010 %
1$
#528
0$
#529
b1001 %
1$
#530
0$
#531
b1000 %
1$
#532
0$
#533
b111 %
1$
#534
0$
#535
b110 %
1$
#536
0$
#537
b101 %
1$
#538
0$
#539
b100 %
1$
#540
0$
#541
b11 %
1$
#542
0$
#543
b10 %
1$
#544
0$
#545
b1 %
1$
#546
0$
#547
b0 %
1$
#548
0$
#549
b1111 %
1!
1$
#550
0$
#551
b1110 %
1$
#552
0$
#553
b1101 %
1$
#554
0$
#555
b1100 %
1$
#556
0$
#557
b1011 %
1$
#558
0$
#559
b1010 %
1$
#560
0$
#561
b1001 %
1$
#562
0$
#563
b1000 %
1$
#564
0$
#565
b111 %
1$
#566
0$
#567
b110 %
1$
#568
0$
#569
b101 %
1$
#570
0$
#571
b100 %
1$
#572
0$
#573
b11 %
1$
#574
0$
#575
b10 %
1$
#576
0$
#577
b1 %
1$
#578
0$
#579
b0 %
1$
#580
0$
#581
b1111 %
0!
1$
#582
0$
#583
b1110 %
1$
#584
0$
#585
b1101 %
1$
#586
0$
#587
b1100 %
1$
#588
0$
#589
b1011 %
1$
#590
0$
#591
b1010 %
1$
#592
0$
#593
b1001 %
1$
#594
0$
#595
b1000 %
1$
#596
0$
#597
b111 %
1$
#598
0$
#599
b110 %
1$
#600
0$
#601
b101 %
1$
#602
0$
#603
b100 %
1$
#604
0$
#605
b11 %
1$
#606
0$
#607
b10 %
1$
#608
0$
#609
b1 %
1$
#610
0$
#611
b0 %
1$
#612
0$
#613
b1111 %
1!
1$
#614
0$
#615
b1110 %
1$
#616
0$
#617
b1101 %
1$
#618
0$
#619
b1100 %
1$
#620
0$
#621
b1011 %
1$
#622
0$
#623
b1010 %
1$
#624
0$
#625
b1001 %
1$
#626
0$
#627
b1000 %
1$
#628
0$
#629
b111 %
1$
#630
0$
#631
b110 %
1$
#632
0$
#633
b101 %
1$
#634
0$
#635
b100 %
1$
#636
0$
#637
b11 %
1$
#638
0$
#639
b10 %
1$
#640
0$
#641
b1 %
1$
#642
0$
#643
b0 %
1$
#644
0$
#645
b1111 %
0!
1$
