UART/modules/uart_timer.v

/*

provides 8-bit timer to TX and RX module to synchronize baudrate.


*/


module uart_timer(
		input reg uart_clk, //divided clock, enable line can be avoided because uart_clk is enabled only on RE and TE
		input reg[7:0] timerInitVal, //initial value for timer, timer is reloaded with this value after overflow
		output reg[7:0] timerCurrentVal //incremented real-time value of timer
	);

always @(timerInitVal)
begin
	timerCurrentVal <= timerInitVal;

end


always @(posedge uart_clk)
begin
	if(timerCurrentVal != 8'd255)
		timerCurrentVal <= timerCurrentVal + 8'b1;
	else
		timerCurrentVal <= timerInitVal;

end

endmodule

UART/testbenches/uart_timer_tb.v



module uart_timer_tb;

reg uart_clk;
reg[7:0] timerInitVal;
wire[7:0] timerCurrentVal;



uart_timer U0(.uart_clk(uart_clk), .timerInitVal(timerInitVal), .timerCurrentVal(timerCurrentVal));


always #1 uart_clk = ~uart_clk;

initial begin

$dumpfile("uart_timer.vcd");
$dumpvars();


timerInitVal = 8'd253; //initialize timer first
#1;
uart_clk = 0; 		//after that RE or TE is enabled

#50;

$finish;

end

endmodule

UART/VCD/uart_timer.vcd
$date
	Tue Jun  2 21:06:03 2026
$end
$version
	Icarus Verilog
$end
$timescale
	1s
$end
$scope module uart_timer_tb $end
$var wire 8 ! timerCurrentVal [7:0] $end
$var reg 8 " timerInitVal [7:0] $end
$var reg 1 # uart_clk $end
$scope module U0 $end
$var wire 8 $ timerInitVal [7:0] $end
$var wire 1 # uart_clk $end
$var reg 8 % timerCurrentVal [7:0] $end
$upscope $end
$upscope $end
$enddefinitions $end
$comment Show the parameter values. $end
$dumpall
$end
#0
$dumpvars
b11111101 %
b11111101 $
x#
b11111101 "
b11111101 !
$end
#1
0#
#2
b11111110 !
b11111110 %
1#
#3
0#
#4
b11111111 !
b11111111 %
1#
#5
0#
#6
b11111101 !
b11111101 %
1#
#7
0#
#8
b11111110 !
b11111110 %
1#
#9
0#
#10
b11111111 !
b11111111 %
1#
#11
0#
#12
b11111101 !
b11111101 %
1#
#13
0#
#14
b11111110 !
b11111110 %
1#
#15
0#
#16
b11111111 !
b11111111 %
1#
#17
0#
#18
b11111101 !
b11111101 %
1#
#19
0#
#20
b11111110 !
b11111110 %
1#
#21
0#
#22
b11111111 !
b11111111 %
1#
#23
0#
#24
b11111101 !
b11111101 %
1#
#25
0#
#26
b11111110 !
b11111110 %
1#
#27
0#
#28
b11111111 !
b11111111 %
1#
#29
0#
#30
b11111101 !
b11111101 %
1#
#31
0#
#32
b11111110 !
b11111110 %
1#
#33
0#
#34
b11111111 !
b11111111 %
1#
#35
0#
#36
b11111101 !
b11111101 %
1#
#37
0#
#38
b11111110 !
b11111110 %
1#
#39
0#
#40
b11111111 !
b11111111 %
1#
#41
0#
#42
b11111101 !
b11111101 %
1#
#43
0#
#44
b11111110 !
b11111110 %
1#
#45
0#
#46
b11111111 !
b11111111 %
1#
#47
0#
#48
b11111101 !
b11111101 %
1#
#49
0#
#50
b11111110 !
b11111110 %
1#
