UART/modules/RX/RXshift.v

module RXshiftreg(input reg enableIN, 	// external signal to enable RXshift block
		output reg ready, 	// output signal to mention RXshift is ready to take date to transmit
		input reg[7:0] timerCurrentVal, //current value of timer register
		input reg[7:0] timerInitVal, 	//initial value of timer register, this value is initialized to the uart-timer and the timer autoreloads this value on overflow
		input reg RX, 			//RX output pin
		output reg[7:0] RXbuff		//buffer that stores recieved data
		);

reg[7:0] smplngTime; //the time at which RX pin should be sampled
reg[9:0] RXrawbuff;  //shift register buffer, includes start bit and stop bit along with data
reg[3:0] counter;    //stores the number of bits to recieve in current frame

reg[7:0] samp;



// initializing registers on enable
always @(posedge enableIN)
begin

if((((timerCurrentVal-timerInitVal) + (256-timerCurrentVal))/2'd2)%2==1)

 smplngTime <= (((256 - timerInitVal)/2) + 1) >= (256 - timerCurrentVal) ? timerInitVal + ((((256 - timerInitVal)/2) + 1) - (256 - timerCurrentVal)) : timerCurrentVal + (((256 - timerInitVal)/2) + 1); //midpoint = (255-timerInitVal)/2
//((midpoint + 1) - (255-timerCurrentVal)) + timerInitVal


else
	 smplngTime <= ((256 - timerInitVal)/2) >= (256 - timerCurrentVal) ? timerInitVal + ((((256 - timerInitVal)/2)) - (256 - timerCurrentVal)) : timerCurrentVal + ((256 - timerInitVal)/2);


//setting sampling time, calculated inorder to sample RX in middle of a bit by considering the time (timerCurrentVal) when RXshiftreg block was enabled







	counter <= 4'd10; 	//initialized counter, total 10 bits to recieve in a frame
	ready <= 1'b0;	  	//pulling ready signal 0, indicates parent module that th RXshiftreg module is BUSY
	RXrawbuff <= 10'd0; 	//initializes rawbuff
	RXbuff <= 8'd0; 	//initializes RXbuff
end


always @(counter)
begin

if(enableIN == 1'b1 && counter == 4'd0)
begin
	RXbuff <= RXrawbuff[8:1];
	ready <= 1'b1;
end

end



//shift register main block
always @(timerCurrentVal)
begin

//updates rawbuff by shifting and recieving bit, counter decremented on sampling of a bit to keep no. of bits left to recieve
if(enableIN == 1'b1 && timerCurrentVal == smplngTime && counter != 4'd0)
begin
	RXrawbuff <= {RX, RXrawbuff[9:1]};
	counter <= counter - 1'b1;

end



//ends reception as soon as counter reaches 0 ie, recieved a complete frame and transfers data to RXbuff after trimming start and stop bits, block is then ready to recieve next frame


end

endmodule

UART/modules/RX/RXtop.v

// RX top module

module RXtop(input reg RE, //Reception Enable signal, enable = 1
	   input reg RX,   //RX pin
	   output reg RI,  //Reception Interrupt connected to port ready
	   output wire[7:0] RXbuff, //recieved data buffer
	   input reg[7:0] timerCurrentVal,    //timer current value, produced by uart-timer
	   input reg[7:0] timerInitVal,//initial value for timer
	   input reg RI_in	    //signal to pull down RI externally
	);

	reg[1:0] state;	   //state variable
	reg RX_ckt_enable; //enable signal for RXshiftreg
	wire RX_ckt_ready; //ready signal from RXshiftreg
	


//instantiation

// RXshiftreg
RXshiftreg R0(.enableIN(RX_ckt_enable), .ready(RX_ckt_ready), .timerCurrentVal(timerCurrentVal), .timerInitVal(timerInitVal), .RX(RX), .RXbuff(RXbuff));
	

//pulls RI LOW when RI_in is pulled low, this is to clear RI externally
always @(negedge RI_in)
begin
	RI <= RI_in;
end


//initializes state when RE enabled
always @(RE)
	begin
		if(RE==1)
			state <= 2'b00;
	end




//RX main FSM
always @(RE, RX, RI, RX_ckt_ready, timerCurrentVal)
	begin
		case(state)
			
			// IDLE
			2'b00 : begin
				// goes to state START when RE enabled, also initializes RI
				  if(RE==1)begin
					RI<=0;
					state <= 2'b01;
					end
				  else if(RE==0)
				  begin
					state <= 2'b00;
				end
				  end

			// START
			2'b01 : begin
				//jumps to state RECIEVE when RX pin gets start-bit (0)
				  if(RE==1 && RI==0 && RX==0)
					begin
					state <= 2'b10;
					RX_ckt_enable <= 1;
					end
	
				//returns to state IDLE if RE pulled low
				  else if(RE==0)
					state <= 2'b00;
				  end

			// RECIEVE
			2'b10 : begin
				//returns to state IDLE if RE pulled low
				  if(RE==0)
					state <= 2'b00;
				  //if(RE==1 && RI==0)
					//begin
					//RX_ckt_enable <= 1; //enables reception block
					//end

				//when reception completed, shiftreg writes RX_ckt_ready = 1, so, RI is made 1, shiftreg disabled and jumps to state STOP
				  if(RE==1 && RX_ckt_ready==1) //ready high?  RI=1;
					begin
					RI <= 1'b1;
					RX_ckt_enable <= 0; //disables reception block
					state <= 2'b11;
					end

				end
			

			// STOP
			2'b11 : begin
				//returns to state IDLE if RE pulled low
				  if(RE==0)
					state <= 2'b00;

				//when RI is cleared externally, jumps to state START
				  else if(RE==1)
					begin
					if(RI==0)
						state <= 2'b01;
					end
				  end
		endcase

	end
endmodule

UART/modules/TX/TXshift.v



module TXshift(
	input reg[7:0] timerCurrentVal, //real-time output of uart-timer
	input reg[7:0] TXbuff, 		//buffer for TX, data to transmit is written to this buffer
	input reg TXshiftenable, 	//signals the TX block to start transmitting, when TXshiftenable = 1, block enabled
	input reg clk, 			//master clock signal
	output reg TXshiftready, 	//Driven by this block to signal that TX has been completed, when TXshiftready = 1, TX completed
	output reg TX 			//output TX pin
);

reg[7:0] timeToShift; //stores the sampled value of timerCurrentVal when block is enabled, the shifting and consequently TX of a bit occurs when the timerCurrentVal is equal to this value
reg[9:0] TXbuffshift; //shift register buffer with added start bit and stop bit, start-bit + TXbuff + stop-bit
reg[3:0] counter;     //used to record the number of bits transmitted

always @(posedge TXshiftenable)
begin
 	// loading the shift register, ie., setting up the frame
	TXbuffshift[8:1] <= TXbuff;
	TXbuffshift[9] <= 1'b1;
	TXbuffshift[0] <= 1'b0;

	TXshiftready <= 1'b0;   // pulling the TXshiftready to 0, indicates that the block is BUSY
	timeToShift <= timerCurrentVal;
	counter <= 4'd10; 	// initialized with 10, because the total transmission in 10 bits
	TX <= 1; 		// initializes TX, to erase the UNKNOWN state
end


always @(timerCurrentVal)
begin	
			if(TXshiftenable==1 && counter!=0 && timerCurrentVal==timeToShift)
				begin
				TX <= TXbuffshift[0]; 			//transmitting the LSB
				TXbuffshift <= {1'b1, TXbuffshift[9:1]};// shifting
				counter <= counter - 4'b0001; 		//counter decremented by 1 per transmission
				end

			case({TXshiftenable,counter})		
				5'b10000 : begin 		// when counter reaches 0, ie., when all bits are finished transmitting
					if(timerCurrentVal==timeToShift)
					begin
						TXshiftready <= 1'b1; // block is ready for new data
					end
				end
				5'b0xxxx : TXshiftready <= 1'b1;      // block is ready because the block was disabled externally
			endcase
end
endmodule

UART/modules/TX/TXtop.v

//TX top module

module TXtop(
	input reg[7:0] timerCurrentVal, //real-time output of uart-timer
	input reg[7:0] TXbuff,		//buffer for TX, data to transmit is written to this buffer
	input reg TE,			//TX enable
	input wire TI_in, 		//External line that pulls TI low, pulled low for short time
	output reg TI,			//TX interrupt
	output wire TX,			//TX pin
	input clk,			//master clock signal
	input wire pwrite		//pwrite line from APB interface, used to signal the change in TXbuff
);

reg[1:0] state; //TX FSM state variable

reg TXCH; //internal register that signals change in TXbuff
reg TXshiftenable; //enable signal, input for TXshift
wire TXshiftready; //ready signal output from TXshift
	
//instantiation of TXshift module
TXshift A1(.timerCurrentVal(timerCurrentVal), .TXbuff(TXbuff), .TXshiftenable(TXshiftenable), .clk(clk), .TXshiftready(TXshiftready), .TX(TX));


//TXCH made HIGH after when there is a write operation on TXbuff
always @(negedge pwrite)
begin
if(pwrite==0)
TXCH <= 1;
end

//initialization of some reg
always @(posedge TE)
begin
state <= 2'b00;
TXshiftenable <= 0;
TI <= 0;
end


//keeps the TXshiftenable complementary to TXshiftready of TXshift module
//
always @(TXshiftready)
begin
if(TXshiftready==1)
	TXshiftenable <= 0;
end


//TI (output) made LOW externally, done by pulling down TI_in
always @(negedge TI_in)
begin
	TI <= TI_in;
end



//TX FSM
always @(clk)
begin

case(state)

// IDLE state
2'b00 : begin
	if(TE==1) //goes to state START when TE enabled
		state <= 2'b01;

end

// START state
2'b01 : begin

	//goes to state IDLE whenever TE disabled
	if(TE==0)
		state <= 2'b00;

	//goes to next state (TRANSMIT) after there is a write operation to TXbuff
	else if(TXCH==1)
		begin
			state <= 2'b10;
			TXshiftenable <= 0; //disabled TXshift
		end
	end

// TRANSMIT state
2'b10 : begin

	//goes to state IDLE
	if(TE==0)
		state <= 2'b00;

	//enables TXshift & pulls down TXCH when TXshift is ready to take data
	else if(TXshiftenable==0 && TXCH==1)
		begin
		TXshiftenable <= 1;
		TXCH <= 0;
		end

	//goes to state START if TXshift is already enabled, that state further disables the TXshift and settles to state TRANSMIT, this is done to restart
	//the transmission with new data even in the middle of an ongoing transmission.
	else if(TXshiftenable==1 && TXCH==1)
		state <= 2'b01;

	//normal case when TXshift finish transmission, interrupt generated and goes to START state and wait there for change in TXbuff
	else if(TXshiftready==1)
		begin
		TI <= 1;
		state <= 2'b01;
		end

end

endcase

end



endmodule

UART/modules/uart_timer.v

/*

provides 8-bit timer to TX and RX module to synchronize baudrate.


*/


module uart_timer(
		input reg uart_clk, //divided clock, enable line can be avoided because uart_clk is enabled only on RE and TE
		input reg[7:0] timerInitVal, //initial value for timer, timer is reloaded with this value after overflow
		output reg[7:0] timerCurrentVal //incremented real-time value of timer
	);

always @(timerInitVal)
begin
	timerCurrentVal <= timerInitVal;

end


always @(posedge uart_clk)
begin
	if(timerCurrentVal != 8'd255)
		timerCurrentVal <= timerCurrentVal + 8'b1;
	else
		timerCurrentVal <= timerInitVal;

end

endmodule

UART/modules/clk_divider.v
/*

problem : initialization of counter and uart_clk
solution : initialized on enabling of RE, TE


problem : RE, TE not enabled simultaneosly, so counter can get resetted without completing half uart_clk cycle
advantage : uart_clk is enabled only when user activates uart. This helps to reduce unwanted power dissipation

FAILED
solution : initializes counter and uart_clk only when any ONE of TE or RE is enabled, ie. the condition is not satisfied 
	   if they are enabled at different times hence counter will not get reset.
trade-off : Assumes TE or RE is disabled when uart usage is over, because if TE or RE is disabled at different times, the condition still satisfies and resets the counter.

KEEPING AS A TRADE OFF assuming that the user is not intending to start uart until both RE and TE are enabled.

*/


//divides master_clk by 32
module clk_divider(input reg master_clk,//master clock of 11.0592MHz
		   output reg uart_clk,	//divided clock for uart
		   input reg RE, 	// used to initialize uart_clk and counter when RE enabled
		   input reg TE 	// used to initialize uart_clk and counter when TE enabled
		);



reg[3:0] counter; //to count number of master_clk posedge
reg flag;

//initializing counter and uart_clk on enabling of RE or TE
always @(TE, RE)
begin

	counter <= 4'b1111; //loaded with 16
	uart_clk <= 0;

end


//main block that divides clock by 32
always @(posedge master_clk)
begin
	//decrements counter on every master_clk posedge
	if(counter!=4'b0)
		counter <= counter - 1;

	//when counter reaches 0, uart clock is inverted and also counter is loaded with d16 for next clock cycle
	if(counter==4'b0000)
	begin
		uart_clk <= ~uart_clk;
		counter <= 4'b1111;
	end
end

endmodule

UART/modules/UARTtop.v



//top module of uart

module uart(
	input wire master_clk,	//master clock
	input reg[7:0] timerInitVal,

	input wire[7:0] TXbuff, //Transmit byte input signal
	input reg TE,		//TX enable signal
	output wire TI,		//Transmission complete interrupt
	input wire TI_in,	//signal to CLEAR TI externally
	output wire TX,		// output to TX pin

	input wire pwrite,	//signal that trigger to start TX, this signal comes
				//from APB interface and TX uses this as a trigger to detect arrival of new data to transmit


	output wire[7:0] RXbuff, //Recieved byte output signal
	input reg RE,		//RX enable signal
	output wire RI,		//Reception interrupt
	input wire RI_in,	//signal to CLEAR RI externally
	input reg RX		// input from RX pin
	);


/* =============INSTANTIATIONS============== */



//clock divider instantiation, this block divides the master clock by 32
clk_divider C0(.master_clk(master_clk), .uart_clk(uart_clk_div), .RE(RE), .TE(TE));

wire uart_clk;
assign uart_clk = uart_clk_div;


//uart timer instantiation, this block takes the divided clock output from clk_divider(C0) and increments timer synchronously
wire[7:0] timerCurrentValwire;
uart_timer U0(.uart_clk(uart_clk), .timerInitVal(timerInitVal), .timerCurrentVal(timerCurrentValwire));




//TX top module instantiation
TXtop T0(.timerCurrentVal(timerCurrentValwire), .TXbuff(TXbuff), .TE(TE), .TI_in(T_in), .TI(TI), .TX(TX), .clk(master_clk), .pwrite(pwrite));


//RX top module instantiation
RXtop R0(.timerCurrentVal(timerCurrentValwire), .timerInitVal(timerInitVal), .RE(RE), .RX(RX), .RI(RI), .RXbuff(RXbuff), .RI_in(RI_in));





endmodule

UART/testbenches/UART_tb.v


module uart_tb;

reg master_clk;
reg[7:0] timerInitVal;
reg[7:0] TXbuff;
reg TE;
wire TI;
reg TI_in;
wire TX;

reg pwrite;

wire[7:0] RXbuff;
reg RE;
wire RI;
reg RI_in;
reg RX;


reg start;
reg[9:0] RXdata;
integer i;



uart dut(.master_clk(master_clk), .timerInitVal(timerInitVal), .TXbuff(TXbuff), .TE(TE), .TI(TI), .TI_in(TI_in), .TX(TX), .pwrite(pwrite), .RXbuff(RXbuff), .RE(RE), .RI(RI), .RI_in(RI_in), .RX(RX));


// drives TX
always @(start)
begin
	pwrite = 1;
	TE = 1;
	#1;
	TI_in = 1;
	#1;
	TI_in = 0;
	#5;
	TXbuff = 8'b00001101;
	pwrite = 0;

end


integer dly, j;

// drives RX
always @(start)
begin

	dly = 256 - timerInitVal;

	RE = 1;
	#4;

	#1;
	RI_in = 1;
	#50;
	RXdata = 10'b1010010010;


for(integer i=0; i<10; i = i+1)
begin

	j = 0;

	RX = RXdata[i];
	for(integer j=0; j<dly; j = j+1)
		#64;

end

	#190;
	RI_in = 0;
	#2;
	RI_in = 1;
	#64;
	RXdata = 10'b1000000010;

for(integer i=0; i<10; i = i+1)
begin

	j = 0;
	RX = RXdata[i];
	for(integer j=0; j<dly; j = j+1)
		#64;

end


end



always #1 master_clk = ~master_clk;

initial begin

$dumpfile("uart.vcd");
$dumpvars();
start = 0;

master_clk = 0;

timerInitVal = 8'd252; //baud rate 115200

#1;
start = 1;


#20000;

$finish;

end

endmodule

UART/VCD/uart.vcd
$date
	Thu Jun  4 08:58:55 2026
$end
$version
	Icarus Verilog
$end
$timescale
	1s
$end
$scope module uart_tb $end
$var wire 1 ! TX $end
$var wire 1 " TI $end
$var wire 8 # RXbuff [7:0] $end
$var wire 1 $ RI $end
$var reg 1 % RE $end
$var reg 1 & RI_in $end
$var reg 1 ' RX $end
$var reg 10 ( RXdata [9:0] $end
$var reg 1 ) TE $end
$var reg 1 * TI_in $end
$var reg 8 + TXbuff [7:0] $end
$var reg 1 , master_clk $end
$var reg 1 - pwrite $end
$var reg 1 . start $end
$var reg 8 / timerInitVal [7:0] $end
$var integer 32 0 dly [31:0] $end
$var integer 32 1 j [31:0] $end
$scope module dut $end
$var wire 1 % RE $end
$var wire 1 & RI_in $end
$var wire 1 ' RX $end
$var wire 1 ) TE $end
$var wire 1 * TI_in $end
$var wire 8 2 TXbuff [7:0] $end
$var wire 1 3 T_in $end
$var wire 1 , master_clk $end
$var wire 1 - pwrite $end
$var wire 8 4 timerInitVal [7:0] $end
$var wire 1 5 uart_clk $end
$var wire 1 6 uart_clk_div $end
$var wire 8 7 timerCurrentValwire [7:0] $end
$var wire 1 ! TX $end
$var wire 1 " TI $end
$var wire 8 8 RXbuff [7:0] $end
$var wire 1 $ RI $end
$scope module C0 $end
$var wire 1 % RE $end
$var wire 1 ) TE $end
$var wire 1 , master_clk $end
$var reg 4 9 counter [3:0] $end
$var reg 1 6 uart_clk $end
$upscope $end
$scope module R0 $end
$var wire 1 % RE $end
$var wire 1 & RI_in $end
$var wire 1 ' RX $end
$var wire 8 : timerInitVal [7:0] $end
$var wire 8 ; timerCurrentVal [7:0] $end
$var wire 8 < RXbuff [7:0] $end
$var wire 1 = RX_ckt_ready $end
$var reg 1 $ RI $end
$var reg 1 > RX_ckt_enable $end
$var reg 2 ? state [1:0] $end
$scope module R0 $end
$var wire 1 ' RX $end
$var wire 1 > enableIN $end
$var wire 8 @ timerInitVal [7:0] $end
$var wire 8 A timerCurrentVal [7:0] $end
$var reg 8 B RXbuff [7:0] $end
$var reg 10 C RXrawbuff [9:0] $end
$var reg 4 D counter [3:0] $end
$var reg 1 = ready $end
$var reg 8 E smplngTime [7:0] $end
$upscope $end
$upscope $end
$scope module T0 $end
$var wire 1 ) TE $end
$var wire 1 3 TI_in $end
$var wire 8 F TXbuff [7:0] $end
$var wire 1 , clk $end
$var wire 1 - pwrite $end
$var wire 8 G timerCurrentVal [7:0] $end
$var wire 1 H TXshiftready $end
$var wire 1 ! TX $end
$var reg 1 " TI $end
$var reg 1 I TXCH $end
$var reg 1 J TXshiftenable $end
$var reg 2 K state [1:0] $end
$scope module A1 $end
$var wire 8 L TXbuff [7:0] $end
$var wire 1 J TXshiftenable $end
$var wire 1 , clk $end
$var wire 8 M timerCurrentVal [7:0] $end
$var reg 1 ! TX $end
$var reg 10 N TXbuffshift [9:0] $end
$var reg 1 H TXshiftready $end
$var reg 4 O counter [3:0] $end
$var reg 8 P timeToShift [7:0] $end
$upscope $end
$upscope $end
$scope module U0 $end
$var wire 8 Q timerInitVal [7:0] $end
$var wire 1 5 uart_clk $end
$var reg 8 R timerCurrentVal [7:0] $end
$upscope $end
$upscope $end
$scope begin $ivl_for_loop0 $end
$var integer 32 S i [31:0] $end
$scope begin $ivl_for_loop1 $end
$var integer 32 T j [31:0] $end
$upscope $end
$upscope $end
$scope begin $ivl_for_loop2 $end
$var integer 32 U i [31:0] $end
$scope begin $ivl_for_loop3 $end
$var integer 32 V j [31:0] $end
$upscope $end
$upscope $end
$upscope $end
$enddefinitions $end
$comment Show the parameter values. $end
$dumpall
$end
#0
$dumpvars
bx V
bx U
bx T
bx S
b11111100 R
b11111100 Q
bx P
bx O
bx N
b11111100 M
bx L
b0 K
0J
xI
1H
b11111100 G
bx F
bx E
bx D
bx C
bx B
b11111100 A
b11111100 @
b1 ?
x>
x=
bx <
b11111100 ;
b11111100 :
b1111 9
bx 8
b11111100 7
06
05
b11111100 4
z3
bx 2
bx 1
b100 0
b11111100 /
0.
1-
0,
bx +
x*
1)
bx (
x'
x&
1%
0$
bx #
0"
x!
$end
#1
b1110 9
b1 K
1*
1.
1,
#2
0*
0,
#3
b1101 9
1,
#4
0,
#5
b1100 9
1,
1&
#6
0,
#7
b1011 9
1I
1,
0-
b1101 +
b1101 2
b1101 F
b1101 L
#8
b10 K
0,
#9
1!
b1010 O
b11111100 P
0H
b1000011010 N
b1010 9
0I
1J
1,
#10
0,
#11
b1001 9
1,
#12
0,
#13
b1000 9
1,
#14
0,
#15
b111 9
1,
#16
0,
#17
b110 9
1,
#18
0,
#19
b101 9
1,
#20
0,
#21
b100 9
1,
#22
0,
#23
b11 9
1,
#24
0,
#25
b10 9
1,
#26
0,
#27
b1 9
1,
#28
0,
#29
b0 9
1,
#30
0,
#31
b11111101 7
b11111101 ;
b11111101 A
b11111101 G
b11111101 M
b11111101 R
b1111 9
15
16
1,
#32
0,
#33
b1110 9
1,
#34
0,
#35
b1101 9
1,
#36
0,
#37
b1100 9
1,
#38
0,
#39
b1011 9
1,
#40
0,
#41
b1010 9
1,
#42
0,
#43
b1001 9
1,
#44
0,
#45
b1000 9
1,
#46
0,
#47
b111 9
1,
#48
0,
#49
b110 9
1,
#50
0,
#51
b101 9
1,
#52
0,
#53
b100 9
1,
#54
0,
#55
b0 #
b0 8
b0 <
b0 B
b0 C
0=
b1010 D
b11111111 E
b11 9
1>
b10 ?
1,
b0 T
0'
b0 1
b0 S
b1010010010 (
#56
0,
#57
b10 9
1,
#58
0,
#59
b1 9
1,
#60
0,
#61
b0 9
1,
#62
0,
#63
b1111 9
05
06
1,
#64
0,
#65
b1110 9
1,
#66
0,
#67
b1101 9
1,
#68
0,
#69
b1100 9
1,
#70
0,
#71
b1011 9
1,
#72
0,
#73
b1010 9
1,
#74
0,
#75
b1001 9
1,
#76
0,
#77
b1000 9
1,
#78
0,
#79
b111 9
1,
#80
0,
#81
b110 9
1,
#82
0,
#83
b101 9
1,
#84
0,
#85
b100 9
1,
#86
0,
#87
b11 9
1,
#88
0,
#89
b10 9
1,
#90
0,
#91
b1 9
1,
#92
0,
#93
b0 9
1,
#94
0,
#95
b11111110 7
b11111110 ;
b11111110 A
b11111110 G
b11111110 M
b11111110 R
b1111 9
15
16
1,
#96
0,
#97
b1110 9
1,
#98
0,
#99
b1101 9
1,
#100
0,
#101
b1100 9
1,
#102
0,
#103
b1011 9
1,
#104
0,
#105
b1010 9
1,
#106
0,
#107
b1001 9
1,
#108
0,
#109
b1000 9
1,
#110
0,
#111
b111 9
1,
#112
0,
#113
b110 9
1,
#114
0,
#115
b101 9
1,
#116
0,
#117
b100 9
1,
#118
0,
#119
b11 9
1,
b1 T
#120
0,
#121
b10 9
1,
#122
0,
#123
b1 9
1,
#124
0,
#125
b0 9
1,
#126
0,
#127
b1111 9
05
06
1,
#128
0,
#129
b1110 9
1,
#130
0,
#131
b1101 9
1,
#132
0,
#133
b1100 9
1,
#134
0,
#135
b1011 9
1,
#136
0,
#137
b1010 9
1,
#138
0,
#139
b1001 9
1,
#140
0,
#141
b1000 9
1,
#142
0,
#143
b111 9
1,
#144
0,
#145
b110 9
1,
#146
0,
#147
b101 9
1,
#148
0,
#149
b100 9
1,
#150
0,
#151
b11 9
1,
#152
0,
#153
b10 9
1,
#154
0,
#155
b1 9
1,
#156
0,
#157
b0 9
1,
#158
0,
#159
b1001 D
b11111111 7
b11111111 ;
b11111111 A
b11111111 G
b11111111 M
b11111111 R
b1111 9
15
16
1,
#160
0,
#161
b1110 9
1,
#162
0,
#163
b1101 9
1,
#164
0,
#165
b1100 9
1,
#166
0,
#167
b1011 9
1,
#168
0,
#169
b1010 9
1,
#170
0,
#171
b1001 9
1,
#172
0,
#173
b1000 9
1,
#174
0,
#175
b111 9
1,
#176
0,
#177
b110 9
1,
#178
0,
#179
b101 9
1,
#180
0,
#181
b100 9
1,
#182
0,
#183
b11 9
1,
b10 T
#184
0,
#185
b10 9
1,
#186
0,
#187
b1 9
1,
#188
0,
#189
b0 9
1,
#190
0,
#191
b1111 9
05
06
1,
#192
0,
#193
b1110 9
1,
#194
0,
#195
b1101 9
1,
#196
0,
#197
b1100 9
1,
#198
0,
#199
b1011 9
1,
#200
0,
#201
b1010 9
1,
#202
0,
#203
b1001 9
1,
#204
0,
#205
b1000 9
1,
#206
0,
#207
b111 9
1,
#208
0,
#209
b110 9
1,
#210
0,
#211
b101 9
1,
#212
0,
#213
b100 9
1,
#214
0,
#215
b11 9
1,
#216
0,
#217
b10 9
1,
#218
0,
#219
b1 9
1,
#220
0,
#221
b0 9
1,
#222
0,
#223
b1001 O
b1100001101 N
0!
b11111100 7
b11111100 ;
b11111100 A
b11111100 G
b11111100 M
b11111100 R
b1111 9
15
16
1,
#224
0,
#225
b1110 9
1,
#226
0,
#227
b1101 9
1,
#228
0,
#229
b1100 9
1,
#230
0,
#231
b1011 9
1,
#232
0,
#233
b1010 9
1,
#234
0,
#235
b1001 9
1,
#236
0,
#237
b1000 9
1,
#238
0,
#239
b111 9
1,
#240
0,
#241
b110 9
1,
#242
0,
#243
b101 9
1,
#244
0,
#245
b100 9
1,
#246
0,
#247
b11 9
1,
b11 T
#248
0,
#249
b10 9
1,
#250
0,
#251
b1 9
1,
#252
0,
#253
b0 9
1,
#254
0,
#255
b1111 9
05
06
1,
#256
0,
#257
b1110 9
1,
#258
0,
#259
b1101 9
1,
#260
0,
#261
b1100 9
1,
#262
0,
#263
b1011 9
1,
#264
0,
#265
b1010 9
1,
#266
0,
#267
b1001 9
1,
#268
0,
#269
b1000 9
1,
#270
0,
#271
b111 9
1,
#272
0,
#273
b110 9
1,
#274
0,
#275
b101 9
1,
#276
0,
#277
b100 9
1,
#278
0,
#279
b11 9
1,
#280
0,
#281
b10 9
1,
#282
0,
#283
b1 9
1,
#284
0,
#285
b0 9
1,
#286
0,
#287
b11111101 7
b11111101 ;
b11111101 A
b11111101 G
b11111101 M
b11111101 R
b1111 9
15
16
1,
#288
0,
#289
b1110 9
1,
#290
0,
#291
b1101 9
1,
#292
0,
#293
b1100 9
1,
#294
0,
#295
b1011 9
1,
#296
0,
#297
b1010 9
1,
#298
0,
#299
b1001 9
1,
#300
0,
#301
b1000 9
1,
#302
0,
#303
b111 9
1,
#304
0,
#305
b110 9
1,
#306
0,
#307
b101 9
1,
#308
0,
#309
b100 9
1,
#310
0,
#311
b11 9
1,
1'
b1 S
b0 T
#312
0,
#313
b10 9
1,
#314
0,
#315
b1 9
1,
#316
0,
#317
b0 9
1,
#318
0,
#319
b1111 9
05
06
1,
#320
0,
#321
b1110 9
1,
#322
0,
#323
b1101 9
1,
#324
0,
#325
b1100 9
1,
#326
0,
#327
b1011 9
1,
#328
0,
#329
b1010 9
1,
#330
0,
#331
b1001 9
1,
#332
0,
#333
b1000 9
1,
#334
0,
#335
b111 9
1,
#336
0,
#337
b110 9
1,
#338
0,
#339
b101 9
1,
#340
0,
#341
b100 9
1,
#342
0,
#343
b11 9
1,
#344
0,
#345
b10 9
1,
#346
0,
#347
b1 9
1,
#348
0,
#349
b0 9
1,
#350
0,
#351
b11111110 7
b11111110 ;
b11111110 A
b11111110 G
b11111110 M
b11111110 R
b1111 9
15
16
1,
#352
0,
#353
b1110 9
1,
#354
0,
#355
b1101 9
1,
#356
0,
#357
b1100 9
1,
#358
0,
#359
b1011 9
1,
#360
0,
#361
b1010 9
1,
#362
0,
#363
b1001 9
1,
#364
0,
#365
b1000 9
1,
#366
0,
#367
b111 9
1,
#368
0,
#369
b110 9
1,
#370
0,
#371
b101 9
1,
#372
0,
#373
b100 9
1,
#374
0,
#375
b11 9
1,
b1 T
#376
0,
#377
b10 9
1,
#378
0,
#379
b1 9
1,
#380
0,
#381
b0 9
1,
#382
0,
#383
b1111 9
05
06
1,
#384
0,
#385
b1110 9
1,
#386
0,
#387
b1101 9
1,
#388
0,
#389
b1100 9
1,
#390
0,
#391
b1011 9
1,
#392
0,
#393
b1010 9
1,
#394
0,
#395
b1001 9
1,
#396
0,
#397
b1000 9
1,
#398
0,
#399
b111 9
1,
#400
0,
#401
b110 9
1,
#402
0,
#403
b101 9
1,
#404
0,
#405
b100 9
1,
#406
0,
#407
b11 9
1,
#408
0,
#409
b10 9
1,
#410
0,
#411
b1 9
1,
#412
0,
#413
b0 9
1,
#414
0,
#415
b1000 D
b1000000000 C
b11111111 7
b11111111 ;
b11111111 A
b11111111 G
b11111111 M
b11111111 R
b1111 9
15
16
1,
#416
0,
#417
b1110 9
1,
#418
0,
#419
b1101 9
1,
#420
0,
#421
b1100 9
1,
#422
0,
#423
b1011 9
1,
#424
0,
#425
b1010 9
1,
#426
0,
#427
b1001 9
1,
#428
0,
#429
b1000 9
1,
#430
0,
#431
b111 9
1,
#432
0,
#433
b110 9
1,
#434
0,
#435
b101 9
1,
#436
0,
#437
b100 9
1,
#438
0,
#439
b11 9
1,
b10 T
#440
0,
#441
b10 9
1,
#442
0,
#443
b1 9
1,
#444
0,
#445
b0 9
1,
#446
0,
#447
b1111 9
05
06
1,
#448
0,
#449
b1110 9
1,
#450
0,
#451
b1101 9
1,
#452
0,
#453
b1100 9
1,
#454
0,
#455
b1011 9
1,
#456
0,
#457
b1010 9
1,
#458
0,
#459
b1001 9
1,
#460
0,
#461
b1000 9
1,
#462
0,
#463
b111 9
1,
#464
0,
#465
b110 9
1,
#466
0,
#467
b101 9
1,
#468
0,
#469
b100 9
1,
#470
0,
#471
b11 9
1,
#472
0,
#473
b10 9
1,
#474
0,
#475
b1 9
1,
#476
0,
#477
b0 9
1,
#478
0,
#479
b1000 O
b1110000110 N
1!
b11111100 7
b11111100 ;
b11111100 A
b11111100 G
b11111100 M
b11111100 R
b1111 9
15
16
1,
#480
0,
#481
b1110 9
1,
#482
0,
#483
b1101 9
1,
#484
0,
#485
b1100 9
1,
#486
0,
#487
b1011 9
1,
#488
0,
#489
b1010 9
1,
#490
0,
#491
b1001 9
1,
#492
0,
#493
b1000 9
1,
#494
0,
#495
b111 9
1,
#496
0,
#497
b110 9
1,
#498
0,
#499
b101 9
1,
#500
0,
#501
b100 9
1,
#502
0,
#503
b11 9
1,
b11 T
#504
0,
#505
b10 9
1,
#506
0,
#507
b1 9
1,
#508
0,
#509
b0 9
1,
#510
0,
#511
b1111 9
05
06
1,
#512
0,
#513
b1110 9
1,
#514
0,
#515
b1101 9
1,
#516
0,
#517
b1100 9
1,
#518
0,
#519
b1011 9
1,
#520
0,
#521
b1010 9
1,
#522
0,
#523
b1001 9
1,
#524
0,
#525
b1000 9
1,
#526
0,
#527
b111 9
1,
#528
0,
#529
b110 9
1,
#530
0,
#531
b101 9
1,
#532
0,
#533
b100 9
1,
#534
0,
#535
b11 9
1,
#536
0,
#537
b10 9
1,
#538
0,
#539
b1 9
1,
#540
0,
#541
b0 9
1,
#542
0,
#543
b11111101 7
b11111101 ;
b11111101 A
b11111101 G
b11111101 M
b11111101 R
b1111 9
15
16
1,
#544
0,
#545
b1110 9
1,
#546
0,
#547
b1101 9
1,
#548
0,
#549
b1100 9
1,
#550
0,
#551
b1011 9
1,
#552
0,
#553
b1010 9
1,
#554
0,
#555
b1001 9
1,
#556
0,
#557
b1000 9
1,
#558
0,
#559
b111 9
1,
#560
0,
#561
b110 9
1,
#562
0,
#563
b101 9
1,
#564
0,
#565
b100 9
1,
#566
0,
#567
b11 9
1,
0'
b10 S
b0 T
#568
0,
#569
b10 9
1,
#570
0,
#571
b1 9
1,
#572
0,
#573
b0 9
1,
#574
0,
#575
b1111 9
05
06
1,
#576
0,
#577
b1110 9
1,
#578
0,
#579
b1101 9
1,
#580
0,
#581
b1100 9
1,
#582
0,
#583
b1011 9
1,
#584
0,
#585
b1010 9
1,
#586
0,
#587
b1001 9
1,
#588
0,
#589
b1000 9
1,
#590
0,
#591
b111 9
1,
#592
0,
#593
b110 9
1,
#594
0,
#595
b101 9
1,
#596
0,
#597
b100 9
1,
#598
0,
#599
b11 9
1,
#600
0,
